Workbook

Sheet Dashboard
A1: WEALTH GLIDE PATH — QUADRANT ROTATION FRAMEWORK
A2: Age-based risk glide with regime-conditional return engine | Backtest Jan 2007–Sep 2026 | Prepared September 09, 2026 | Forward ledger live
A4: Inputs — edit yellow cells
A5: Current age | C5: 25
A6: Target end age | C6: 65
A7: Starting balance ($) | C7: 11000
A8: Year-1 monthly contribution ($) | C8: 1500
A9: Contribution cap ($/mo) | C9: 40000
A10: Backtest return haircut | C10: 0.25 | D10: discount on backtested returns; 0% = raw backtest
A11: ST tax rate on gains (fed+state) | C11: 0.24 | D11: rotation gains are ~all short-term (median regime 2 months) — taxed annually
A12: LT cap-gains rate | C12: 0.15 | D12: applied to buy-and-hold benchmarks at liquidation (Comparison)
A13: Risk glide path — choose a tier for each 5-year block
A14: ="Age "&($C$5+0*5)&"–"&($C$5+1*5) | C14: VAGG | E14: =MAX(0,MIN(5,($C$6-$C$5)-0*5))/MAX(1,$C$6-$C$5) | F14: =INDEX(Settings!$D$13:$D$16,MATCH($C14,Settings!$A$13:$A$16,0)) | G14: =INDEX(Settings!$G$13:$G$16,MATCH($C14,Settings!$A$13:$A$16,0))
A15: ="Age "&($C$5+1*5)&"–"&($C$5+2*5) | C15: VAGG | E15: =MAX(0,MIN(5,($C$6-$C$5)-1*5))/MAX(1,$C$6-$C$5) | F15: =INDEX(Settings!$D$13:$D$16,MATCH($C15,Settings!$A$13:$A$16,0)) | G15: =INDEX(Settings!$G$13:$G$16,MATCH($C15,Settings!$A$13:$A$16,0))
A16: ="Age "&($C$5+2*5)&"–"&($C$5+3*5) | C16: AGG | E16: =MAX(0,MIN(5,($C$6-$C$5)-2*5))/MAX(1,$C$6-$C$5) | F16: =INDEX(Settings!$D$13:$D$16,MATCH($C16,Settings!$A$13:$A$16,0)) | G16: =INDEX(Settings!$G$13:$G$16,MATCH($C16,Settings!$A$13:$A$16,0))
A17: ="Age "&($C$5+3*5)&"–"&($C$5+4*5) | C17: AGG | E17: =MAX(0,MIN(5,($C$6-$C$5)-3*5))/MAX(1,$C$6-$C$5) | F17: =INDEX(Settings!$D$13:$D$16,MATCH($C17,Settings!$A$13:$A$16,0)) | G17: =INDEX(Settings!$G$13:$G$16,MATCH($C17,Settings!$A$13:$A$16,0))
A18: ="Age "&($C$5+4*5)&"–"&($C$5+5*5) | C18: MOD | E18: =MAX(0,MIN(5,($C$6-$C$5)-4*5))/MAX(1,$C$6-$C$5) | F18: =INDEX(Settings!$D$13:$D$16,MATCH($C18,Settings!$A$13:$A$16,0)) | G18: =INDEX(Settings!$G$13:$G$16,MATCH($C18,Settings!$A$13:$A$16,0))
A19: ="Age "&($C$5+5*5)&"–"&($C$5+6*5) | C19: MOD | E19: =MAX(0,MIN(5,($C$6-$C$5)-5*5))/MAX(1,$C$6-$C$5) | F19: =INDEX(Settings!$D$13:$D$16,MATCH($C19,Settings!$A$13:$A$16,0)) | G19: =INDEX(Settings!$G$13:$G$16,MATCH($C19,Settings!$A$13:$A$16,0))
A20: ="Age "&($C$5+6*5)&"–"&($C$5+7*5) | C20: MOD | E20: =MAX(0,MIN(5,($C$6-$C$5)-6*5))/MAX(1,$C$6-$C$5) | F20: =INDEX(Settings!$D$13:$D$16,MATCH($C20,Settings!$A$13:$A$16,0)) | G20: =INDEX(Settings!$G$13:$G$16,MATCH($C20,Settings!$A$13:$A$16,0))
A21: ="Age "&($C$5+7*5)&"–"&($C$5+8*5) | C21: CONS | E21: =MAX(0,MIN(5,($C$6-$C$5)-7*5))/MAX(1,$C$6-$C$5) | F21: =INDEX(Settings!$D$13:$D$16,MATCH($C21,Settings!$A$13:$A$16,0)) | G21: =INDEX(Settings!$G$13:$G$16,MATCH($C21,Settings!$A$13:$A$16,0))
A22: Default glide: VAGG to 35, AGG to 45, MOD to 60, CONS to 65. Grey columns = weight in horizon / tier stats (used by Statistics).
A24: Outcome (after-tax, after-haircut)
A25: Current tier / net growth rate | C25: =$C$14&" · "&TEXT($F$14,"0.0%")&"/yr"
A26: Current monthly contribution | C26: =MIN($C$9,Settings!$B$19)
A27: Expected balance at end age | C27: =INDEX(Projection!$E:$E,(($C$6-$C$5)*12)+4)
A28: Low / High (±1 s.e.) | C28: =TEXT(INDEX(Projection!$F:$F,(($C$6-$C$5)*12)+4),"$#,##0")&" / "&TEXT(INDEX(Projection!$G:$G,(($C$6-$C$5)*12)+4),"$#,##0")
A29: Total contributed | C29: =$C$7+SUM(Projection!$D$5:INDEX(Projection!$D:$D,(($C$6-$C$5)*12)+4))
A30: Investment growth | C30: =C27-C29
A31: Wealth multiple (balance / contributed) | C31: =IF(C29=0,0,C27/C29)
A33: Backtest-derived planning model; pending forward validation (paper ledger). Deep statistics on the next sheet. Not investment advice.

Sheet Statistics
A1: DEEP STATISTICS — BACKTEST EVIDENCE & REGIME ANALYTICS
A2: Matrix v9 (gold instrument by regime — bullion in Reflation, miners in Deflation for AGG/VAGG; AGG Reflation leverage on the energy leg; conditional-duration S, washout-conditional rebound slice, R momentum tilt, regime-gated short book behind a global include-shorts switch), monthly-only execution — intra-month mechanisms tested and rejected under honest T+1 modeling. Leveraged instruments simulated pre-2010. Out-of-sample framework validation: 1987-2007 replication. Forward: paper/ledger.csv.
A4: 1 · Full-period & crisis-year performance
A5: Strategy | B5: CAGR | C5: Sortino | D5: Sharpe | E5: Max DD | F5: Beta | G5: 2008 | H5: 2020 | I5: 2022 | J5: 2025 | K5: 2026 YTD
A6: CONS | B6: 0.0981 | C6: 1.6213 | D6: 1.1678 | E6: -0.1021 | F6: 0.1699 | G6: 0.1382 | H6: 0.1297 | I6: 0.0187 | J6: 0.2063 | K6: 0.1358
A7: MOD | B7: 0.1543 | C7: 1.7335 | D7: 1.2537 | E7: -0.1433 | F7: 0.3303 | G7: 0.1463 | H7: 0.2998 | I7: 0.0115 | J7: 0.3012 | K7: 0.1986
A8: AGG | B8: 0.2728 | C8: 1.4118 | D8: 1.0856 | E8: -0.3315 | F8: 0.6431 | G8: 0.3462 | H8: 0.867 | I8: -0.0931 | J8: 0.4396 | K8: 0.3178
A9: VAGG | B9: 0.3532 | C9: 1.22 | D9: 0.9646 | E9: -0.4682 | F9: 1.0242 | G9: 0.4413 | H9: 1.402 | I9: -0.3106 | J9: 0.4968 | K9: 0.3254
A10: SPY B&H | B10: 0.1098 | C10: 0.6869 | D10: 0.5612 | E10: -0.5519 | F10: 1 | G10: -0.3679 | H10: 0.1833 | I10: -0.1818 | J10: 0.1772 | K10: 0.1347
A11: QQQ B&H | B11: 0.1645 | C11: 0.9613 | D11: 0.7405 | E11: -0.534 | F11: 1.0473 | G11: -0.4173 | H11: 0.4841 | I11: -0.3258 | J11: 0.2077 | K11: 0.2085
A13: 2 · Annualized return by tier × regime (conditional)
B14: Growth | C14: Reflation | D14: Stagflation | E14: Deflation | F14: Blended (mix)
A15: CONS | B15: =(1+Data!B6)^12-1 | C15: =(1+Data!C6)^12-1 | D15: =(1+Data!D6)^12-1 | E15: =(1+Data!E6)^12-1 | F15: =Settings!C13
A16: MOD | B16: =(1+Data!B7)^12-1 | C16: =(1+Data!C7)^12-1 | D16: =(1+Data!D7)^12-1 | E16: =(1+Data!E7)^12-1 | F16: =Settings!C14
A17: AGG | B17: =(1+Data!B8)^12-1 | C17: =(1+Data!C8)^12-1 | D17: =(1+Data!D8)^12-1 | E17: =(1+Data!E8)^12-1 | F17: =Settings!C15
A18: VAGG | B18: =(1+Data!B9)^12-1 | C18: =(1+Data!C9)^12-1 | D18: =(1+Data!D9)^12-1 | E18: =(1+Data!E9)^12-1 | F18: =Settings!C16
A20: 3 · In-regime Sharpe by tier × regime
B21: Growth | C21: Reflation | D21: Stagflation | E21: Deflation
A22: CONS | B22: =IF(Data!B13=0,0,((1+Data!B6)^12-1-Data!$B$23)/(Data!B13*SQRT(12))) | C22: =IF(Data!C13=0,0,((1+Data!C6)^12-1-Data!$B$23)/(Data!C13*SQRT(12))) | D22: =IF(Data!D13=0,0,((1+Data!D6)^12-1-Data!$B$23)/(Data!D13*SQRT(12))) | E22: =IF(Data!E13=0,0,((1+Data!E6)^12-1-Data!$B$23)/(Data!E13*SQRT(12)))
A23: MOD | B23: =IF(Data!B14=0,0,((1+Data!B7)^12-1-Data!$B$23)/(Data!B14*SQRT(12))) | C23: =IF(Data!C14=0,0,((1+Data!C7)^12-1-Data!$B$23)/(Data!C14*SQRT(12))) | D23: =IF(Data!D14=0,0,((1+Data!D7)^12-1-Data!$B$23)/(Data!D14*SQRT(12))) | E23: =IF(Data!E14=0,0,((1+Data!E7)^12-1-Data!$B$23)/(Data!E14*SQRT(12)))
A24: AGG | B24: =IF(Data!B15=0,0,((1+Data!B8)^12-1-Data!$B$23)/(Data!B15*SQRT(12))) | C24: =IF(Data!C15=0,0,((1+Data!C8)^12-1-Data!$B$23)/(Data!C15*SQRT(12))) | D24: =IF(Data!D15=0,0,((1+Data!D8)^12-1-Data!$B$23)/(Data!D15*SQRT(12))) | E24: =IF(Data!E15=0,0,((1+Data!E8)^12-1-Data!$B$23)/(Data!E15*SQRT(12)))
A25: VAGG | B25: =IF(Data!B16=0,0,((1+Data!B9)^12-1-Data!$B$23)/(Data!B16*SQRT(12))) | C25: =IF(Data!C16=0,0,((1+Data!C9)^12-1-Data!$B$23)/(Data!C16*SQRT(12))) | D25: =IF(Data!D16=0,0,((1+Data!D9)^12-1-Data!$B$23)/(Data!D16*SQRT(12))) | E25: =IF(Data!E16=0,0,((1+Data!E9)^12-1-Data!$B$23)/(Data!E16*SQRT(12)))
A27: 4 · Regime structure | B27: Growth | C27: Reflation | D27: Stagflation | E27: Deflation
A28: Share of months | B28: =Data!B20 | C28: =Data!C20 | D28: =Data!D20 | E28: =Data!E20
A29: Avg duration (months) | B29: =Data!B21 | C29: =Data!C21 | D29: =Data!D21 | E29: =Data!E21
A31: 5 · Outcome distribution at end age (glide-weighted approximation)
A32: Glide-weighted annual return (after-tax) | B32: =SUMPRODUCT(Dashboard!$E$14:$E$21,Dashboard!$F$14:$F$21)
A33: Glide-weighted annual sd | B33: =SUMPRODUCT(Dashboard!$E$14:$E$21,Dashboard!$G$14:$G$21)
A35: Percentile | B35: z | C35: Annual rate | D35: Final balance (approx)
A36: P10 | B36: -1.2816 | C36: =$B$32+B36*$B$33/SQRT(MAX(1,Settings!$B$9)) | D36: =IF(ABS(((1+C36)^(1/12)-1)-Settings!$B$60)<0.000001,Dashboard!$C$7*(1+((1+C36)^(1/12)-1))^(Settings!$B$9*12)+Dashboard!$C$8*(Settings!$B$9*12)*(1+((1+C36)^(1/12)-1))^((Settings!$B$9*12)-1),Dashboard!$C$7*(1+((1+C36)^(1/12)-1))^(Settings!$B$9*12)+Dashboard!$C$8*(((1+((1+C36)^(1/12)-1))^(Settings!$B$9*12))-((1+Settings!$B$60)^(Settings!$B$9*12)))/(((1+C36)^(1/12)-1)-Settings!$B$60))
A37: P25 | B37: -0.6745 | C37: =$B$32+B37*$B$33/SQRT(MAX(1,Settings!$B$9)) | D37: =IF(ABS(((1+C37)^(1/12)-1)-Settings!$B$60)<0.000001,Dashboard!$C$7*(1+((1+C37)^(1/12)-1))^(Settings!$B$9*12)+Dashboard!$C$8*(Settings!$B$9*12)*(1+((1+C37)^(1/12)-1))^((Settings!$B$9*12)-1),Dashboard!$C$7*(1+((1+C37)^(1/12)-1))^(Settings!$B$9*12)+Dashboard!$C$8*(((1+((1+C37)^(1/12)-1))^(Settings!$B$9*12))-((1+Settings!$B$60)^(Settings!$B$9*12)))/(((1+C37)^(1/12)-1)-Settings!$B$60))
A38: P50 (median) | B38: 0 | C38: =$B$32+B38*$B$33/SQRT(MAX(1,Settings!$B$9)) | D38: =IF(ABS(((1+C38)^(1/12)-1)-Settings!$B$60)<0.000001,Dashboard!$C$7*(1+((1+C38)^(1/12)-1))^(Settings!$B$9*12)+Dashboard!$C$8*(Settings!$B$9*12)*(1+((1+C38)^(1/12)-1))^((Settings!$B$9*12)-1),Dashboard!$C$7*(1+((1+C38)^(1/12)-1))^(Settings!$B$9*12)+Dashboard!$C$8*(((1+((1+C38)^(1/12)-1))^(Settings!$B$9*12))-((1+Settings!$B$60)^(Settings!$B$9*12)))/(((1+C38)^(1/12)-1)-Settings!$B$60))
A39: P75 | B39: 0.6745 | C39: =$B$32+B39*$B$33/SQRT(MAX(1,Settings!$B$9)) | D39: =IF(ABS(((1+C39)^(1/12)-1)-Settings!$B$60)<0.000001,Dashboard!$C$7*(1+((1+C39)^(1/12)-1))^(Settings!$B$9*12)+Dashboard!$C$8*(Settings!$B$9*12)*(1+((1+C39)^(1/12)-1))^((Settings!$B$9*12)-1),Dashboard!$C$7*(1+((1+C39)^(1/12)-1))^(Settings!$B$9*12)+Dashboard!$C$8*(((1+((1+C39)^(1/12)-1))^(Settings!$B$9*12))-((1+Settings!$B$60)^(Settings!$B$9*12)))/(((1+C39)^(1/12)-1)-Settings!$B$60))
A40: P90 | B40: 1.2816 | C40: =$B$32+B40*$B$33/SQRT(MAX(1,Settings!$B$9)) | D40: =IF(ABS(((1+C40)^(1/12)-1)-Settings!$B$60)<0.000001,Dashboard!$C$7*(1+((1+C40)^(1/12)-1))^(Settings!$B$9*12)+Dashboard!$C$8*(Settings!$B$9*12)*(1+((1+C40)^(1/12)-1))^((Settings!$B$9*12)-1),Dashboard!$C$7*(1+((1+C40)^(1/12)-1))^(Settings!$B$9*12)+Dashboard!$C$8*(((1+((1+C40)^(1/12)-1))^(Settings!$B$9*12))-((1+Settings!$B$60)^(Settings!$B$9*12)))/(((1+C40)^(1/12)-1)-Settings!$B$60))
A42: Percentiles band the average growth rate; within-horizon drawdowns exceed these paths (see Max DD above). Contribution schedule approximated as smooth growth, cap ignored — Projection is exact.

Sheet Comparison
A1: COMPARISON — COMMON PORTFOLIOS VS THE GLIDE PATH
A2: Identical window (Jan 2007–Sep 2026), dividends included. Benchmark stats are data (blue); tier rows link to Statistics (green).
A4: 1 · Historical risk & return
A5: Portfolio | B5: CAGR | C5: Sortino | D5: Sharpe | E5: Max DD | F5: Beta | G5: 2008 | H5: 2022
A6: S&P 500 (SPY) | B6: 0.1098 | C6: 0.69 | D6: 0.56 | E6: -0.5519 | F6: 1 | G6: -0.3679 | H6: -0.1818
A7: Nasdaq 100 (QQQ) | B7: 0.1645 | C7: 0.96 | D7: 0.74 | E7: -0.534 | F7: 1.05 | G7: -0.4173 | H7: -0.3258
A8: Dow Jones (DIA) | B8: 0.0978 | C8: 0.64 | D8: 0.51 | E8: -0.5187 | F8: 0.92 | G8: -0.3214 | H8: -0.0702
A9: 60/40 (SPY/AGG) | B9: 0.0817 | C9: 0.73 | D9: 0.59 | E9: -0.347 | F9: 0.6 | G9: -0.1997 | H9: -0.1562
A10: All bonds (AGG) | B10: 0.0298 | C10: 0.36 | D10: 0.3 | E10: -0.1843 | F10: 0 | G10: 0.079 | H10: -0.1302
A11: Gold (GLD) | B11: 0.0998 | C11: 0.71 | D11: 0.53 | E11: -0.4556 | F11: 0.05 | G11: 0.0492 | H11: -0.0077
A12: Rotation CONS | B12: =Statistics!B6 | C12: =Statistics!C6 | D12: =Statistics!D6 | E12: =Statistics!E6 | F12: =Statistics!F6 | G12: =Statistics!G6 | H12: =Statistics!I6
A13: Rotation MOD | B13: =Statistics!B7 | C13: =Statistics!C7 | D13: =Statistics!D7 | E13: =Statistics!E7 | F13: =Statistics!F7 | G13: =Statistics!G7 | H13: =Statistics!I7
A14: Rotation AGG | B14: =Statistics!B8 | C14: =Statistics!C8 | D14: =Statistics!D8 | E14: =Statistics!E8 | F14: =Statistics!F8 | G14: =Statistics!G8 | H14: =Statistics!I8
A15: Rotation VAGG | B15: =Statistics!B9 | C15: =Statistics!C9 | D15: =Statistics!D9 | E15: =Statistics!E9 | F15: =Statistics!F9 | G15: =Statistics!G9 | H15: =Statistics!I9
A17: 2 · Forward-looking — after tax, same haircut, same contributions, to end age | H17: Benchmark haircut: | I17: =Dashboard!$C$10
A18: Portfolio | B18: Raw hist. CAGR | C18: Net expected | D18: Monthly | E18: Pre-tax balance | F18: After-tax balance | G18: vs glide path
A19: S&P 500 (SPY) | B19: 0.1098 | C19: =B19*(1-$I$17) | D19: =(1+C19)^(1/12)-1 | E19: =IF(ABS($D$19-Settings!$B$60)<0.000001,Dashboard!$C$7*(1+$D$19)^(Settings!$B$9*12)+Dashboard!$C$8*(Settings!$B$9*12)*(1+$D$19)^((Settings!$B$9*12)-1),Dashboard!$C$7*(1+$D$19)^(Settings!$B$9*12)+Dashboard!$C$8*(((1+$D$19)^(Settings!$B$9*12))-((1+Settings!$B$60)^(Settings!$B$9*12)))/($D$19-Settings!$B$60)) | F19: =$I$30+MAX(0,E19-$I$30)*(1-Dashboard!$C$12) | G19: =F19/$F$29-1
A20: Nasdaq 100 (QQQ) | B20: 0.1645 | C20: =B20*(1-$I$17) | D20: =(1+C20)^(1/12)-1 | E20: =IF(ABS($D$20-Settings!$B$60)<0.000001,Dashboard!$C$7*(1+$D$20)^(Settings!$B$9*12)+Dashboard!$C$8*(Settings!$B$9*12)*(1+$D$20)^((Settings!$B$9*12)-1),Dashboard!$C$7*(1+$D$20)^(Settings!$B$9*12)+Dashboard!$C$8*(((1+$D$20)^(Settings!$B$9*12))-((1+Settings!$B$60)^(Settings!$B$9*12)))/($D$20-Settings!$B$60)) | F20: =$I$30+MAX(0,E20-$I$30)*(1-Dashboard!$C$12) | G20: =F20/$F$29-1
A21: Dow Jones (DIA) | B21: 0.0978 | C21: =B21*(1-$I$17) | D21: =(1+C21)^(1/12)-1 | E21: =IF(ABS($D$21-Settings!$B$60)<0.000001,Dashboard!$C$7*(1+$D$21)^(Settings!$B$9*12)+Dashboard!$C$8*(Settings!$B$9*12)*(1+$D$21)^((Settings!$B$9*12)-1),Dashboard!$C$7*(1+$D$21)^(Settings!$B$9*12)+Dashboard!$C$8*(((1+$D$21)^(Settings!$B$9*12))-((1+Settings!$B$60)^(Settings!$B$9*12)))/($D$21-Settings!$B$60)) | F21: =$I$30+MAX(0,E21-$I$30)*(1-Dashboard!$C$12) | G21: =F21/$F$29-1
A22: 60/40 (SPY/AGG) | B22: 0.0817 | C22: =B22*(1-$I$17) | D22: =(1+C22)^(1/12)-1 | E22: =IF(ABS($D$22-Settings!$B$60)<0.000001,Dashboard!$C$7*(1+$D$22)^(Settings!$B$9*12)+Dashboard!$C$8*(Settings!$B$9*12)*(1+$D$22)^((Settings!$B$9*12)-1),Dashboard!$C$7*(1+$D$22)^(Settings!$B$9*12)+Dashboard!$C$8*(((1+$D$22)^(Settings!$B$9*12))-((1+Settings!$B$60)^(Settings!$B$9*12)))/($D$22-Settings!$B$60)) | F22: =$I$30+MAX(0,E22-$I$30)*(1-Dashboard!$C$12) | G22: =F22/$F$29-1
A23: All bonds (AGG) | B23: 0.0298 | C23: =B23*(1-$I$17) | D23: =(1+C23)^(1/12)-1 | E23: =IF(ABS($D$23-Settings!$B$60)<0.000001,Dashboard!$C$7*(1+$D$23)^(Settings!$B$9*12)+Dashboard!$C$8*(Settings!$B$9*12)*(1+$D$23)^((Settings!$B$9*12)-1),Dashboard!$C$7*(1+$D$23)^(Settings!$B$9*12)+Dashboard!$C$8*(((1+$D$23)^(Settings!$B$9*12))-((1+Settings!$B$60)^(Settings!$B$9*12)))/($D$23-Settings!$B$60)) | F23: =$I$30+MAX(0,E23-$I$30)*(1-Dashboard!$C$12) | G23: =F23/$F$29-1
A24: Gold (GLD) | B24: 0.0998 | C24: =B24*(1-$I$17) | D24: =(1+C24)^(1/12)-1 | E24: =IF(ABS($D$24-Settings!$B$60)<0.000001,Dashboard!$C$7*(1+$D$24)^(Settings!$B$9*12)+Dashboard!$C$8*(Settings!$B$9*12)*(1+$D$24)^((Settings!$B$9*12)-1),Dashboard!$C$7*(1+$D$24)^(Settings!$B$9*12)+Dashboard!$C$8*(((1+$D$24)^(Settings!$B$9*12))-((1+Settings!$B$60)^(Settings!$B$9*12)))/($D$24-Settings!$B$60)) | F24: =$I$30+MAX(0,E24-$I$30)*(1-Dashboard!$C$12) | G24: =F24/$F$29-1
A25: Rotation CONS | B25: =Statistics!$B$6 | C25: =Settings!$D$13 | D25: =(1+C25)^(1/12)-1 | E25: =IF(ABS($D$25-Settings!$B$60)<0.000001,Dashboard!$C$7*(1+$D$25)^(Settings!$B$9*12)+Dashboard!$C$8*(Settings!$B$9*12)*(1+$D$25)^((Settings!$B$9*12)-1),Dashboard!$C$7*(1+$D$25)^(Settings!$B$9*12)+Dashboard!$C$8*(((1+$D$25)^(Settings!$B$9*12))-((1+Settings!$B$60)^(Settings!$B$9*12)))/($D$25-Settings!$B$60)) | F25: =E25 | G25: =F25/$F$29-1
A26: Rotation MOD | B26: =Statistics!$B$7 | C26: =Settings!$D$14 | D26: =(1+C26)^(1/12)-1 | E26: =IF(ABS($D$26-Settings!$B$60)<0.000001,Dashboard!$C$7*(1+$D$26)^(Settings!$B$9*12)+Dashboard!$C$8*(Settings!$B$9*12)*(1+$D$26)^((Settings!$B$9*12)-1),Dashboard!$C$7*(1+$D$26)^(Settings!$B$9*12)+Dashboard!$C$8*(((1+$D$26)^(Settings!$B$9*12))-((1+Settings!$B$60)^(Settings!$B$9*12)))/($D$26-Settings!$B$60)) | F26: =E26 | G26: =F26/$F$29-1
A27: Rotation AGG | B27: =Statistics!$B$8 | C27: =Settings!$D$15 | D27: =(1+C27)^(1/12)-1 | E27: =IF(ABS($D$27-Settings!$B$60)<0.000001,Dashboard!$C$7*(1+$D$27)^(Settings!$B$9*12)+Dashboard!$C$8*(Settings!$B$9*12)*(1+$D$27)^((Settings!$B$9*12)-1),Dashboard!$C$7*(1+$D$27)^(Settings!$B$9*12)+Dashboard!$C$8*(((1+$D$27)^(Settings!$B$9*12))-((1+Settings!$B$60)^(Settings!$B$9*12)))/($D$27-Settings!$B$60)) | F27: =E27 | G27: =F27/$F$29-1
A28: Rotation VAGG | B28: =Statistics!$B$9 | C28: =Settings!$D$16 | D28: =(1+C28)^(1/12)-1 | E28: =IF(ABS($D$28-Settings!$B$60)<0.000001,Dashboard!$C$7*(1+$D$28)^(Settings!$B$9*12)+Dashboard!$C$8*(Settings!$B$9*12)*(1+$D$28)^((Settings!$B$9*12)-1),Dashboard!$C$7*(1+$D$28)^(Settings!$B$9*12)+Dashboard!$C$8*(((1+$D$28)^(Settings!$B$9*12))-((1+Settings!$B$60)^(Settings!$B$9*12)))/($D$28-Settings!$B$60)) | F28: =E28 | G28: =F28/$F$29-1
A29: YOUR GLIDE PATH (exact) | B29: =Statistics!$B$32 | F29: =INDEX(Projection!$E:$E,(Settings!$B$9*12)+4)
H30: Total contributed: | I30: =Dashboard!$C$7+12*SUM(Settings!$B$19:INDEX(Settings!$B$19:$B$58,MIN(40,Settings!$B$9)))
A31: Taxable-account model: rotation tiers taxed ANNUALLY at the ST rate (median regime 2 months — gains are short-term); buy-and-hold benchmarks compound pre-tax and pay the LT rate on gains at liquidation (deferral included; small dividend-tax drag omitted, slightly favoring benchmarks). One haircut on every row.

Sheet Projection
A1: Age-Aware Wealth Projection
A2: Each month uses the risk tier from the Dashboard glide path for that age. Low/High = ±1 s.e. on the average growth rate.
A4: Month | B4: Age | C4: Tier | D4: Contribution | E4: Expected | F4: Low | G4: High
A5: 1 | B5: =Dashboard!$C$5+(1-1)/12 | C5: =INDEX(Dashboard!$C$14:$C$21,MIN(8,INT((1-1)/60)+1)) | D5: =MIN(Dashboard!$C$9,INDEX(Settings!$B$19:$B$58,MIN(40,INT((1-1)/12)+1))) | E5: =Dashboard!$C$7*(1+INDEX(Settings!$E$13:$E$16,MATCH(C5,Settings!$A$13:$A$16,0)))+D5 | F5: =Dashboard!$C$7*(1+INDEX(Settings!$I$13:$I$16,MATCH(C5,Settings!$A$13:$A$16,0)))+D5 | G5: =Dashboard!$C$7*(1+INDEX(Settings!$J$13:$J$16,MATCH(C5,Settings!$A$13:$A$16,0)))+D5
A6: 2 | B6: =Dashboard!$C$5+(2-1)/12 | C6: =INDEX(Dashboard!$C$14:$C$21,MIN(8,INT((2-1)/60)+1)) | D6: =MIN(Dashboard!$C$9,INDEX(Settings!$B$19:$B$58,MIN(40,INT((2-1)/12)+1))) | E6: =E5*(1+INDEX(Settings!$E$13:$E$16,MATCH(C6,Settings!$A$13:$A$16,0)))+D6 | F6: =F5*(1+INDEX(Settings!$I$13:$I$16,MATCH(C6,Settings!$A$13:$A$16,0)))+D6 | G6: =G5*(1+INDEX(Settings!$J$13:$J$16,MATCH(C6,Settings!$A$13:$A$16,0)))+D6
A7: 3 | B7: =Dashboard!$C$5+(3-1)/12 | C7: =INDEX(Dashboard!$C$14:$C$21,MIN(8,INT((3-1)/60)+1)) | D7: =MIN(Dashboard!$C$9,INDEX(Settings!$B$19:$B$58,MIN(40,INT((3-1)/12)+1))) | E7: =E6*(1+INDEX(Settings!$E$13:$E$16,MATCH(C7,Settings!$A$13:$A$16,0)))+D7 | F7: =F6*(1+INDEX(Settings!$I$13:$I$16,MATCH(C7,Settings!$A$13:$A$16,0)))+D7 | G7: =G6*(1+INDEX(Settings!$J$13:$J$16,MATCH(C7,Settings!$A$13:$A$16,0)))+D7
A8: 4 | B8: =Dashboard!$C$5+(4-1)/12 | C8: =INDEX(Dashboard!$C$14:$C$21,MIN(8,INT((4-1)/60)+1)) | D8: =MIN(Dashboard!$C$9,INDEX(Settings!$B$19:$B$58,MIN(40,INT((4-1)/12)+1))) | E8: =E7*(1+INDEX(Settings!$E$13:$E$16,MATCH(C8,Settings!$A$13:$A$16,0)))+D8 | F8: =F7*(1+INDEX(Settings!$I$13:$I$16,MATCH(C8,Settings!$A$13:$A$16,0)))+D8 | G8: =G7*(1+INDEX(Settings!$J$13:$J$16,MATCH(C8,Settings!$A$13:$A$16,0)))+D8
A9: 5 | B9: =Dashboard!$C$5+(5-1)/12 | C9: =INDEX(Dashboard!$C$14:$C$21,MIN(8,INT((5-1)/60)+1)) | D9: =MIN(Dashboard!$C$9,INDEX(Settings!$B$19:$B$58,MIN(40,INT((5-1)/12)+1))) | E9: =E8*(1+INDEX(Settings!$E$13:$E$16,MATCH(C9,Settings!$A$13:$A$16,0)))+D9 | F9: =F8*(1+INDEX(Settings!$I$13:$I$16,MATCH(C9,Settings!$A$13:$A$16,0)))+D9 | G9: =G8*(1+INDEX(Settings!$J$13:$J$16,MATCH(C9,Settings!$A$13:$A$16,0)))+D9
A10: 6 | B10: =Dashboard!$C$5+(6-1)/12 | C10: =INDEX(Dashboard!$C$14:$C$21,MIN(8,INT((6-1)/60)+1)) | D10: =MIN(Dashboard!$C$9,INDEX(Settings!$B$19:$B$58,MIN(40,INT((6-1)/12)+1))) | E10: =E9*(1+INDEX(Settings!$E$13:$E$16,MATCH(C10,Settings!$A$13:$A$16,0)))+D10 | F10: =F9*(1+INDEX(Settings!$I$13:$I$16,MATCH(C10,Settings!$A$13:$A$16,0)))+D10 | G10: =G9*(1+INDEX(Settings!$J$13:$J$16,MATCH(C10,Settings!$A$13:$A$16,0)))+D10
A11: 7 | B11: =Dashboard!$C$5+(7-1)/12 | C11: =INDEX(Dashboard!$C$14:$C$21,MIN(8,INT((7-1)/60)+1)) | D11: =MIN(Dashboard!$C$9,INDEX(Settings!$B$19:$B$58,MIN(40,INT((7-1)/12)+1))) | E11: =E10*(1+INDEX(Settings!$E$13:$E$16,MATCH(C11,Settings!$A$13:$A$16,0)))+D11 | F11: =F10*(1+INDEX(Settings!$I$13:$I$16,MATCH(C11,Settings!$A$13:$A$16,0)))+D11 | G11: =G10*(1+INDEX(Settings!$J$13:$J$16,MATCH(C11,Settings!$A$13:$A$16,0)))+D11
A12: 8 | B12: =Dashboard!$C$5+(8-1)/12 | C12: =INDEX(Dashboard!$C$14:$C$21,MIN(8,INT((8-1)/60)+1)) | D12: =MIN(Dashboard!$C$9,INDEX(Settings!$B$19:$B$58,MIN(40,INT((8-1)/12)+1))) | E12: =E11*(1+INDEX(Settings!$E$13:$E$16,MATCH(C12,Settings!$A$13:$A$16,0)))+D12 | F12: =F11*(1+INDEX(Settings!$I$13:$I$16,MATCH(C12,Settings!$A$13:$A$16,0)))+D12 | G12: =G11*(1+INDEX(Settings!$J$13:$J$16,MATCH(C12,Settings!$A$13:$A$16,0)))+D12
A13: 9 | B13: =Dashboard!$C$5+(9-1)/12 | C13: =INDEX(Dashboard!$C$14:$C$21,MIN(8,INT((9-1)/60)+1)) | D13: =MIN(Dashboard!$C$9,INDEX(Settings!$B$19:$B$58,MIN(40,INT((9-1)/12)+1))) | E13: =E12*(1+INDEX(Settings!$E$13:$E$16,MATCH(C13,Settings!$A$13:$A$16,0)))+D13 | F13: =F12*(1+INDEX(Settings!$I$13:$I$16,MATCH(C13,Settings!$A$13:$A$16,0)))+D13 | G13: =G12*(1+INDEX(Settings!$J$13:$J$16,MATCH(C13,Settings!$A$13:$A$16,0)))+D13
A14: 10 | B14: =Dashboard!$C$5+(10-1)/12 | C14: =INDEX(Dashboard!$C$14:$C$21,MIN(8,INT((10-1)/60)+1)) | D14: =MIN(Dashboard!$C$9,INDEX(Settings!$B$19:$B$58,MIN(40,INT((10-1)/12)+1))) | E14: =E13*(1+INDEX(Settings!$E$13:$E$16,MATCH(C14,Settings!$A$13:$A$16,0)))+D14 | F14: =F13*(1+INDEX(Settings!$I$13:$I$16,MATCH(C14,Settings!$A$13:$A$16,0)))+D14 | G14: =G13*(1+INDEX(Settings!$J$13:$J$16,MATCH(C14,Settings!$A$13:$A$16,0)))+D14
A15: 11 | B15: =Dashboard!$C$5+(11-1)/12 | C15: =INDEX(Dashboard!$C$14:$C$21,MIN(8,INT((11-1)/60)+1)) | D15: =MIN(Dashboard!$C$9,INDEX(Settings!$B$19:$B$58,MIN(40,INT((11-1)/12)+1))) | E15: =E14*(1+INDEX(Settings!$E$13:$E$16,MATCH(C15,Settings!$A$13:$A$16,0)))+D15 | F15: =F14*(1+INDEX(Settings!$I$13:$I$16,MATCH(C15,Settings!$A$13:$A$16,0)))+D15 | G15: =G14*(1+INDEX(Settings!$J$13:$J$16,MATCH(C15,Settings!$A$13:$A$16,0)))+D15
A16: 12 | B16: =Dashboard!$C$5+(12-1)/12 | C16: =INDEX(Dashboard!$C$14:$C$21,MIN(8,INT((12-1)/60)+1)) | D16: =MIN(Dashboard!$C$9,INDEX(Settings!$B$19:$B$58,MIN(40,INT((12-1)/12)+1))) | E16: =E15*(1+INDEX(Settings!$E$13:$E$16,MATCH(C16,Settings!$A$13:$A$16,0)))+D16 | F16: =F15*(1+INDEX(Settings!$I$13:$I$16,MATCH(C16,Settings!$A$13:$A$16,0)))+D16 | G16: =G15*(1+INDEX(Settings!$J$13:$J$16,MATCH(C16,Settings!$A$13:$A$16,0)))+D16
A17: 13 | B17: =Dashboard!$C$5+(13-1)/12 | C17: =INDEX(Dashboard!$C$14:$C$21,MIN(8,INT((13-1)/60)+1)) | D17: =MIN(Dashboard!$C$9,INDEX(Settings!$B$19:$B$58,MIN(40,INT((13-1)/12)+1))) | E17: =E16*(1+INDEX(Settings!$E$13:$E$16,MATCH(C17,Settings!$A$13:$A$16,0)))+D17 | F17: =F16*(1+INDEX(Settings!$I$13:$I$16,MATCH(C17,Settings!$A$13:$A$16,0)))+D17 | G17: =G16*(1+INDEX(Settings!$J$13:$J$16,MATCH(C17,Settings!$A$13:$A$16,0)))+D17
A18: 14 | B18: =Dashboard!$C$5+(14-1)/12 | C18: =INDEX(Dashboard!$C$14:$C$21,MIN(8,INT((14-1)/60)+1)) | D18: =MIN(Dashboard!$C$9,INDEX(Settings!$B$19:$B$58,MIN(40,INT((14-1)/12)+1))) | E18: =E17*(1+INDEX(Settings!$E$13:$E$16,MATCH(C18,Settings!$A$13:$A$16,0)))+D18 | F18: =F17*(1+INDEX(Settings!$I$13:$I$16,MATCH(C18,Settings!$A$13:$A$16,0)))+D18 | G18: =G17*(1+INDEX(Settings!$J$13:$J$16,MATCH(C18,Settings!$A$13:$A$16,0)))+D18
A19: 15 | B19: =Dashboard!$C$5+(15-1)/12 | C19: =INDEX(Dashboard!$C$14:$C$21,MIN(8,INT((15-1)/60)+1)) | D19: =MIN(Dashboard!$C$9,INDEX(Settings!$B$19:$B$58,MIN(40,INT((15-1)/12)+1))) | E19: =E18*(1+INDEX(Settings!$E$13:$E$16,MATCH(C19,Settings!$A$13:$A$16,0)))+D19 | F19: =F18*(1+INDEX(Settings!$I$13:$I$16,MATCH(C19,Settings!$A$13:$A$16,0)))+D19 | G19: =G18*(1+INDEX(Settings!$J$13:$J$16,MATCH(C19,Settings!$A$13:$A$16,0)))+D19
A20: 16 | B20: =Dashboard!$C$5+(16-1)/12 | C20: =INDEX(Dashboard!$C$14:$C$21,MIN(8,INT((16-1)/60)+1)) | D20: =MIN(Dashboard!$C$9,INDEX(Settings!$B$19:$B$58,MIN(40,INT((16-1)/12)+1))) | E20: =E19*(1+INDEX(Settings!$E$13:$E$16,MATCH(C20,Settings!$A$13:$A$16,0)))+D20 | F20: =F19*(1+INDEX(Settings!$I$13:$I$16,MATCH(C20,Settings!$A$13:$A$16,0)))+D20 | G20: =G19*(1+INDEX(Settings!$J$13:$J$16,MATCH(C20,Settings!$A$13:$A$16,0)))+D20
A21: 17 | B21: =Dashboard!$C$5+(17-1)/12 | C21: =INDEX(Dashboard!$C$14:$C$21,MIN(8,INT((17-1)/60)+1)) | D21: =MIN(Dashboard!$C$9,INDEX(Settings!$B$19:$B$58,MIN(40,INT((17-1)/12)+1))) | E21: =E20*(1+INDEX(Settings!$E$13:$E$16,MATCH(C21,Settings!$A$13:$A$16,0)))+D21 | F21: =F20*(1+INDEX(Settings!$I$13:$I$16,MATCH(C21,Settings!$A$13:$A$16,0)))+D21 | G21: =G20*(1+INDEX(Settings!$J$13:$J$16,MATCH(C21,Settings!$A$13:$A$16,0)))+D21
A22: 18 | B22: =Dashboard!$C$5+(18-1)/12 | C22: =INDEX(Dashboard!$C$14:$C$21,MIN(8,INT((18-1)/60)+1)) | D22: =MIN(Dashboard!$C$9,INDEX(Settings!$B$19:$B$58,MIN(40,INT((18-1)/12)+1))) | E22: =E21*(1+INDEX(Settings!$E$13:$E$16,MATCH(C22,Settings!$A$13:$A$16,0)))+D22 | F22: =F21*(1+INDEX(Settings!$I$13:$I$16,MATCH(C22,Settings!$A$13:$A$16,0)))+D22 | G22: =G21*(1+INDEX(Settings!$J$13:$J$16,MATCH(C22,Settings!$A$13:$A$16,0)))+D22
A23: 19 | B23: =Dashboard!$C$5+(19-1)/12 | C23: =INDEX(Dashboard!$C$14:$C$21,MIN(8,INT((19-1)/60)+1)) | D23: =MIN(Dashboard!$C$9,INDEX(Settings!$B$19:$B$58,MIN(40,INT((19-1)/12)+1))) | E23: =E22*(1+INDEX(Settings!$E$13:$E$16,MATCH(C23,Settings!$A$13:$A$16,0)))+D23 | F23: =F22*(1+INDEX(Settings!$I$13:$I$16,MATCH(C23,Settings!$A$13:$A$16,0)))+D23 | G23: =G22*(1+INDEX(Settings!$J$13:$J$16,MATCH(C23,Settings!$A$13:$A$16,0)))+D23
A24: 20 | B24: =Dashboard!$C$5+(20-1)/12 | C24: =INDEX(Dashboard!$C$14:$C$21,MIN(8,INT((20-1)/60)+1)) | D24: =MIN(Dashboard!$C$9,INDEX(Settings!$B$19:$B$58,MIN(40,INT((20-1)/12)+1))) | E24: =E23*(1+INDEX(Settings!$E$13:$E$16,MATCH(C24,Settings!$A$13:$A$16,0)))+D24 | F24: =F23*(1+INDEX(Settings!$I$13:$I$16,MATCH(C24,Settings!$A$13:$A$16,0)))+D24 | G24: =G23*(1+INDEX(Settings!$J$13:$J$16,MATCH(C24,Settings!$A$13:$A$16,0)))+D24
A25: 21 | B25: =Dashboard!$C$5+(21-1)/12 | C25: =INDEX(Dashboard!$C$14:$C$21,MIN(8,INT((21-1)/60)+1)) | D25: =MIN(Dashboard!$C$9,INDEX(Settings!$B$19:$B$58,MIN(40,INT((21-1)/12)+1))) | E25: =E24*(1+INDEX(Settings!$E$13:$E$16,MATCH(C25,Settings!$A$13:$A$16,0)))+D25 | F25: =F24*(1+INDEX(Settings!$I$13:$I$16,MATCH(C25,Settings!$A$13:$A$16,0)))+D25 | G25: =G24*(1+INDEX(Settings!$J$13:$J$16,MATCH(C25,Settings!$A$13:$A$16,0)))+D25
A26: 22 | B26: =Dashboard!$C$5+(22-1)/12 | C26: =INDEX(Dashboard!$C$14:$C$21,MIN(8,INT((22-1)/60)+1)) | D26: =MIN(Dashboard!$C$9,INDEX(Settings!$B$19:$B$58,MIN(40,INT((22-1)/12)+1))) | E26: =E25*(1+INDEX(Settings!$E$13:$E$16,MATCH(C26,Settings!$A$13:$A$16,0)))+D26 | F26: =F25*(1+INDEX(Settings!$I$13:$I$16,MATCH(C26,Settings!$A$13:$A$16,0)))+D26 | G26: =G25*(1+INDEX(Settings!$J$13:$J$16,MATCH(C26,Settings!$A$13:$A$16,0)))+D26
A27: 23 | B27: =Dashboard!$C$5+(23-1)/12 | C27: =INDEX(Dashboard!$C$14:$C$21,MIN(8,INT((23-1)/60)+1)) | D27: =MIN(Dashboard!$C$9,INDEX(Settings!$B$19:$B$58,MIN(40,INT((23-1)/12)+1))) | E27: =E26*(1+INDEX(Settings!$E$13:$E$16,MATCH(C27,Settings!$A$13:$A$16,0)))+D27 | F27: =F26*(1+INDEX(Settings!$I$13:$I$16,MATCH(C27,Settings!$A$13:$A$16,0)))+D27 | G27: =G26*(1+INDEX(Settings!$J$13:$J$16,MATCH(C27,Settings!$A$13:$A$16,0)))+D27
A28: 24 | B28: =Dashboard!$C$5+(24-1)/12 | C28: =INDEX(Dashboard!$C$14:$C$21,MIN(8,INT((24-1)/60)+1)) | D28: =MIN(Dashboard!$C$9,INDEX(Settings!$B$19:$B$58,MIN(40,INT((24-1)/12)+1))) | E28: =E27*(1+INDEX(Settings!$E$13:$E$16,MATCH(C28,Settings!$A$13:$A$16,0)))+D28 | F28: =F27*(1+INDEX(Settings!$I$13:$I$16,MATCH(C28,Settings!$A$13:$A$16,0)))+D28 | G28: =G27*(1+INDEX(Settings!$J$13:$J$16,MATCH(C28,Settings!$A$13:$A$16,0)))+D28
A29: 25 | B29: =Dashboard!$C$5+(25-1)/12 | C29: =INDEX(Dashboard!$C$14:$C$21,MIN(8,INT((25-1)/60)+1)) | D29: =MIN(Dashboard!$C$9,INDEX(Settings!$B$19:$B$58,MIN(40,INT((25-1)/12)+1))) | E29: =E28*(1+INDEX(Settings!$E$13:$E$16,MATCH(C29,Settings!$A$13:$A$16,0)))+D29 | F29: =F28*(1+INDEX(Settings!$I$13:$I$16,MATCH(C29,Settings!$A$13:$A$16,0)))+D29 | G29: =G28*(1+INDEX(Settings!$J$13:$J$16,MATCH(C29,Settings!$A$13:$A$16,0)))+D29
A30: 26 | B30: =Dashboard!$C$5+(26-1)/12 | C30: =INDEX(Dashboard!$C$14:$C$21,MIN(8,INT((26-1)/60)+1)) | D30: =MIN(Dashboard!$C$9,INDEX(Settings!$B$19:$B$58,MIN(40,INT((26-1)/12)+1))) | E30: =E29*(1+INDEX(Settings!$E$13:$E$16,MATCH(C30,Settings!$A$13:$A$16,0)))+D30 | F30: =F29*(1+INDEX(Settings!$I$13:$I$16,MATCH(C30,Settings!$A$13:$A$16,0)))+D30 | G30: =G29*(1+INDEX(Settings!$J$13:$J$16,MATCH(C30,Settings!$A$13:$A$16,0)))+D30
A31: 27 | B31: =Dashboard!$C$5+(27-1)/12 | C31: =INDEX(Dashboard!$C$14:$C$21,MIN(8,INT((27-1)/60)+1)) | D31: =MIN(Dashboard!$C$9,INDEX(Settings!$B$19:$B$58,MIN(40,INT((27-1)/12)+1))) | E31: =E30*(1+INDEX(Settings!$E$13:$E$16,MATCH(C31,Settings!$A$13:$A$16,0)))+D31 | F31: =F30*(1+INDEX(Settings!$I$13:$I$16,MATCH(C31,Settings!$A$13:$A$16,0)))+D31 | G31: =G30*(1+INDEX(Settings!$J$13:$J$16,MATCH(C31,Settings!$A$13:$A$16,0)))+D31
A32: 28 | B32: =Dashboard!$C$5+(28-1)/12 | C32: =INDEX(Dashboard!$C$14:$C$21,MIN(8,INT((28-1)/60)+1)) | D32: =MIN(Dashboard!$C$9,INDEX(Settings!$B$19:$B$58,MIN(40,INT((28-1)/12)+1))) | E32: =E31*(1+INDEX(Settings!$E$13:$E$16,MATCH(C32,Settings!$A$13:$A$16,0)))+D32 | F32: =F31*(1+INDEX(Settings!$I$13:$I$16,MATCH(C32,Settings!$A$13:$A$16,0)))+D32 | G32: =G31*(1+INDEX(Settings!$J$13:$J$16,MATCH(C32,Settings!$A$13:$A$16,0)))+D32
A33: 29 | B33: =Dashboard!$C$5+(29-1)/12 | C33: =INDEX(Dashboard!$C$14:$C$21,MIN(8,INT((29-1)/60)+1)) | D33: =MIN(Dashboard!$C$9,INDEX(Settings!$B$19:$B$58,MIN(40,INT((29-1)/12)+1))) | E33: =E32*(1+INDEX(Settings!$E$13:$E$16,MATCH(C33,Settings!$A$13:$A$16,0)))+D33 | F33: =F32*(1+INDEX(Settings!$I$13:$I$16,MATCH(C33,Settings!$A$13:$A$16,0)))+D33 | G33: =G32*(1+INDEX(Settings!$J$13:$J$16,MATCH(C33,Settings!$A$13:$A$16,0)))+D33
A34: 30 | B34: =Dashboard!$C$5+(30-1)/12 | C34: =INDEX(Dashboard!$C$14:$C$21,MIN(8,INT((30-1)/60)+1)) | D34: =MIN(Dashboard!$C$9,INDEX(Settings!$B$19:$B$58,MIN(40,INT((30-1)/12)+1))) | E34: =E33*(1+INDEX(Settings!$E$13:$E$16,MATCH(C34,Settings!$A$13:$A$16,0)))+D34 | F34: =F33*(1+INDEX(Settings!$I$13:$I$16,MATCH(C34,Settings!$A$13:$A$16,0)))+D34 | G34: =G33*(1+INDEX(Settings!$J$13:$J$16,MATCH(C34,Settings!$A$13:$A$16,0)))+D34
A35: 31 | B35: =Dashboard!$C$5+(31-1)/12 | C35: =INDEX(Dashboard!$C$14:$C$21,MIN(8,INT((31-1)/60)+1)) | D35: =MIN(Dashboard!$C$9,INDEX(Settings!$B$19:$B$58,MIN(40,INT((31-1)/12)+1))) | E35: =E34*(1+INDEX(Settings!$E$13:$E$16,MATCH(C35,Settings!$A$13:$A$16,0)))+D35 | F35: =F34*(1+INDEX(Settings!$I$13:$I$16,MATCH(C35,Settings!$A$13:$A$16,0)))+D35 | G35: =G34*(1+INDEX(Settings!$J$13:$J$16,MATCH(C35,Settings!$A$13:$A$16,0)))+D35
A36: 32 | B36: =Dashboard!$C$5+(32-1)/12 | C36: =INDEX(Dashboard!$C$14:$C$21,MIN(8,INT((32-1)/60)+1)) | D36: =MIN(Dashboard!$C$9,INDEX(Settings!$B$19:$B$58,MIN(40,INT((32-1)/12)+1))) | E36: =E35*(1+INDEX(Settings!$E$13:$E$16,MATCH(C36,Settings!$A$13:$A$16,0)))+D36 | F36: =F35*(1+INDEX(Settings!$I$13:$I$16,MATCH(C36,Settings!$A$13:$A$16,0)))+D36 | G36: =G35*(1+INDEX(Settings!$J$13:$J$16,MATCH(C36,Settings!$A$13:$A$16,0)))+D36
A37: 33 | B37: =Dashboard!$C$5+(33-1)/12 | C37: =INDEX(Dashboard!$C$14:$C$21,MIN(8,INT((33-1)/60)+1)) | D37: =MIN(Dashboard!$C$9,INDEX(Settings!$B$19:$B$58,MIN(40,INT((33-1)/12)+1))) | E37: =E36*(1+INDEX(Settings!$E$13:$E$16,MATCH(C37,Settings!$A$13:$A$16,0)))+D37 | F37: =F36*(1+INDEX(Settings!$I$13:$I$16,MATCH(C37,Settings!$A$13:$A$16,0)))+D37 | G37: =G36*(1+INDEX(Settings!$J$13:$J$16,MATCH(C37,Settings!$A$13:$A$16,0)))+D37
A38: 34 | B38: =Dashboard!$C$5+(34-1)/12 | C38: =INDEX(Dashboard!$C$14:$C$21,MIN(8,INT((34-1)/60)+1)) | D38: =MIN(Dashboard!$C$9,INDEX(Settings!$B$19:$B$58,MIN(40,INT((34-1)/12)+1))) | E38: =E37*(1+INDEX(Settings!$E$13:$E$16,MATCH(C38,Settings!$A$13:$A$16,0)))+D38 | F38: =F37*(1+INDEX(Settings!$I$13:$I$16,MATCH(C38,Settings!$A$13:$A$16,0)))+D38 | G38: =G37*(1+INDEX(Settings!$J$13:$J$16,MATCH(C38,Settings!$A$13:$A$16,0)))+D38
A39: 35 | B39: =Dashboard!$C$5+(35-1)/12 | C39: =INDEX(Dashboard!$C$14:$C$21,MIN(8,INT((35-1)/60)+1)) | D39: =MIN(Dashboard!$C$9,INDEX(Settings!$B$19:$B$58,MIN(40,INT((35-1)/12)+1))) | E39: =E38*(1+INDEX(Settings!$E$13:$E$16,MATCH(C39,Settings!$A$13:$A$16,0)))+D39 | F39: =F38*(1+INDEX(Settings!$I$13:$I$16,MATCH(C39,Settings!$A$13:$A$16,0)))+D39 | G39: =G38*(1+INDEX(Settings!$J$13:$J$16,MATCH(C39,Settings!$A$13:$A$16,0)))+D39
A40: 36 | B40: =Dashboard!$C$5+(36-1)/12 | C40: =INDEX(Dashboard!$C$14:$C$21,MIN(8,INT((36-1)/60)+1)) | D40: =MIN(Dashboard!$C$9,INDEX(Settings!$B$19:$B$58,MIN(40,INT((36-1)/12)+1))) | E40: =E39*(1+INDEX(Settings!$E$13:$E$16,MATCH(C40,Settings!$A$13:$A$16,0)))+D40 | F40: =F39*(1+INDEX(Settings!$I$13:$I$16,MATCH(C40,Settings!$A$13:$A$16,0)))+D40 | G40: =G39*(1+INDEX(Settings!$J$13:$J$16,MATCH(C40,Settings!$A$13:$A$16,0)))+D40
A41: 37 | B41: =Dashboard!$C$5+(37-1)/12 | C41: =INDEX(Dashboard!$C$14:$C$21,MIN(8,INT((37-1)/60)+1)) | D41: =MIN(Dashboard!$C$9,INDEX(Settings!$B$19:$B$58,MIN(40,INT((37-1)/12)+1))) | E41: =E40*(1+INDEX(Settings!$E$13:$E$16,MATCH(C41,Settings!$A$13:$A$16,0)))+D41 | F41: =F40*(1+INDEX(Settings!$I$13:$I$16,MATCH(C41,Settings!$A$13:$A$16,0)))+D41 | G41: =G40*(1+INDEX(Settings!$J$13:$J$16,MATCH(C41,Settings!$A$13:$A$16,0)))+D41
A42: 38 | B42: =Dashboard!$C$5+(38-1)/12 | C42: =INDEX(Dashboard!$C$14:$C$21,MIN(8,INT((38-1)/60)+1)) | D42: =MIN(Dashboard!$C$9,INDEX(Settings!$B$19:$B$58,MIN(40,INT((38-1)/12)+1))) | E42: =E41*(1+INDEX(Settings!$E$13:$E$16,MATCH(C42,Settings!$A$13:$A$16,0)))+D42 | F42: =F41*(1+INDEX(Settings!$I$13:$I$16,MATCH(C42,Settings!$A$13:$A$16,0)))+D42 | G42: =G41*(1+INDEX(Settings!$J$13:$J$16,MATCH(C42,Settings!$A$13:$A$16,0)))+D42
A43: 39 | B43: =Dashboard!$C$5+(39-1)/12 | C43: =INDEX(Dashboard!$C$14:$C$21,MIN(8,INT((39-1)/60)+1)) | D43: =MIN(Dashboard!$C$9,INDEX(Settings!$B$19:$B$58,MIN(40,INT((39-1)/12)+1))) | E43: =E42*(1+INDEX(Settings!$E$13:$E$16,MATCH(C43,Settings!$A$13:$A$16,0)))+D43 | F43: =F42*(1+INDEX(Settings!$I$13:$I$16,MATCH(C43,Settings!$A$13:$A$16,0)))+D43 | G43: =G42*(1+INDEX(Settings!$J$13:$J$16,MATCH(C43,Settings!$A$13:$A$16,0)))+D43
A44: 40 | B44: =Dashboard!$C$5+(40-1)/12 | C44: =INDEX(Dashboard!$C$14:$C$21,MIN(8,INT((40-1)/60)+1)) | D44: =MIN(Dashboard!$C$9,INDEX(Settings!$B$19:$B$58,MIN(40,INT((40-1)/12)+1))) | E44: =E43*(1+INDEX(Settings!$E$13:$E$16,MATCH(C44,Settings!$A$13:$A$16,0)))+D44 | F44: =F43*(1+INDEX(Settings!$I$13:$I$16,MATCH(C44,Settings!$A$13:$A$16,0)))+D44 | G44: =G43*(1+INDEX(Settings!$J$13:$J$16,MATCH(C44,Settings!$A$13:$A$16,0)))+D44
A45: 41 | B45: =Dashboard!$C$5+(41-1)/12 | C45: =INDEX(Dashboard!$C$14:$C$21,MIN(8,INT((41-1)/60)+1)) | D45: =MIN(Dashboard!$C$9,INDEX(Settings!$B$19:$B$58,MIN(40,INT((41-1)/12)+1))) | E45: =E44*(1+INDEX(Settings!$E$13:$E$16,MATCH(C45,Settings!$A$13:$A$16,0)))+D45 | F45: =F44*(1+INDEX(Settings!$I$13:$I$16,MATCH(C45,Settings!$A$13:$A$16,0)))+D45 | G45: =G44*(1+INDEX(Settings!$J$13:$J$16,MATCH(C45,Settings!$A$13:$A$16,0)))+D45
A46: 42 | B46: =Dashboard!$C$5+(42-1)/12 | C46: =INDEX(Dashboard!$C$14:$C$21,MIN(8,INT((42-1)/60)+1)) | D46: =MIN(Dashboard!$C$9,INDEX(Settings!$B$19:$B$58,MIN(40,INT((42-1)/12)+1))) | E46: =E45*(1+INDEX(Settings!$E$13:$E$16,MATCH(C46,Settings!$A$13:$A$16,0)))+D46 | F46: =F45*(1+INDEX(Settings!$I$13:$I$16,MATCH(C46,Settings!$A$13:$A$16,0)))+D46 | G46: =G45*(1+INDEX(Settings!$J$13:$J$16,MATCH(C46,Settings!$A$13:$A$16,0)))+D46
A47: 43 | B47: =Dashboard!$C$5+(43-1)/12 | C47: =INDEX(Dashboard!$C$14:$C$21,MIN(8,INT((43-1)/60)+1)) | D47: =MIN(Dashboard!$C$9,INDEX(Settings!$B$19:$B$58,MIN(40,INT((43-1)/12)+1))) | E47: =E46*(1+INDEX(Settings!$E$13:$E$16,MATCH(C47,Settings!$A$13:$A$16,0)))+D47 | F47: =F46*(1+INDEX(Settings!$I$13:$I$16,MATCH(C47,Settings!$A$13:$A$16,0)))+D47 | G47: =G46*(1+INDEX(Settings!$J$13:$J$16,MATCH(C47,Settings!$A$13:$A$16,0)))+D47
A48: 44 | B48: =Dashboard!$C$5+(44-1)/12 | C48: =INDEX(Dashboard!$C$14:$C$21,MIN(8,INT((44-1)/60)+1)) | D48: =MIN(Dashboard!$C$9,INDEX(Settings!$B$19:$B$58,MIN(40,INT((44-1)/12)+1))) | E48: =E47*(1+INDEX(Settings!$E$13:$E$16,MATCH(C48,Settings!$A$13:$A$16,0)))+D48 | F48: =F47*(1+INDEX(Settings!$I$13:$I$16,MATCH(C48,Settings!$A$13:$A$16,0)))+D48 | G48: =G47*(1+INDEX(Settings!$J$13:$J$16,MATCH(C48,Settings!$A$13:$A$16,0)))+D48
A49: 45 | B49: =Dashboard!$C$5+(45-1)/12 | C49: =INDEX(Dashboard!$C$14:$C$21,MIN(8,INT((45-1)/60)+1)) | D49: =MIN(Dashboard!$C$9,INDEX(Settings!$B$19:$B$58,MIN(40,INT((45-1)/12)+1))) | E49: =E48*(1+INDEX(Settings!$E$13:$E$16,MATCH(C49,Settings!$A$13:$A$16,0)))+D49 | F49: =F48*(1+INDEX(Settings!$I$13:$I$16,MATCH(C49,Settings!$A$13:$A$16,0)))+D49 | G49: =G48*(1+INDEX(Settings!$J$13:$J$16,MATCH(C49,Settings!$A$13:$A$16,0)))+D49
A50: 46 | B50: =Dashboard!$C$5+(46-1)/12 | C50: =INDEX(Dashboard!$C$14:$C$21,MIN(8,INT((46-1)/60)+1)) | D50: =MIN(Dashboard!$C$9,INDEX(Settings!$B$19:$B$58,MIN(40,INT((46-1)/12)+1))) | E50: =E49*(1+INDEX(Settings!$E$13:$E$16,MATCH(C50,Settings!$A$13:$A$16,0)))+D50 | F50: =F49*(1+INDEX(Settings!$I$13:$I$16,MATCH(C50,Settings!$A$13:$A$16,0)))+D50 | G50: =G49*(1+INDEX(Settings!$J$13:$J$16,MATCH(C50,Settings!$A$13:$A$16,0)))+D50
A51: 47 | B51: =Dashboard!$C$5+(47-1)/12 | C51: =INDEX(Dashboard!$C$14:$C$21,MIN(8,INT((47-1)/60)+1)) | D51: =MIN(Dashboard!$C$9,INDEX(Settings!$B$19:$B$58,MIN(40,INT((47-1)/12)+1))) | E51: =E50*(1+INDEX(Settings!$E$13:$E$16,MATCH(C51,Settings!$A$13:$A$16,0)))+D51 | F51: =F50*(1+INDEX(Settings!$I$13:$I$16,MATCH(C51,Settings!$A$13:$A$16,0)))+D51 | G51: =G50*(1+INDEX(Settings!$J$13:$J$16,MATCH(C51,Settings!$A$13:$A$16,0)))+D51
A52: 48 | B52: =Dashboard!$C$5+(48-1)/12 | C52: =INDEX(Dashboard!$C$14:$C$21,MIN(8,INT((48-1)/60)+1)) | D52: =MIN(Dashboard!$C$9,INDEX(Settings!$B$19:$B$58,MIN(40,INT((48-1)/12)+1))) | E52: =E51*(1+INDEX(Settings!$E$13:$E$16,MATCH(C52,Settings!$A$13:$A$16,0)))+D52 | F52: =F51*(1+INDEX(Settings!$I$13:$I$16,MATCH(C52,Settings!$A$13:$A$16,0)))+D52 | G52: =G51*(1+INDEX(Settings!$J$13:$J$16,MATCH(C52,Settings!$A$13:$A$16,0)))+D52
A53: 49 | B53: =Dashboard!$C$5+(49-1)/12 | C53: =INDEX(Dashboard!$C$14:$C$21,MIN(8,INT((49-1)/60)+1)) | D53: =MIN(Dashboard!$C$9,INDEX(Settings!$B$19:$B$58,MIN(40,INT((49-1)/12)+1))) | E53: =E52*(1+INDEX(Settings!$E$13:$E$16,MATCH(C53,Settings!$A$13:$A$16,0)))+D53 | F53: =F52*(1+INDEX(Settings!$I$13:$I$16,MATCH(C53,Settings!$A$13:$A$16,0)))+D53 | G53: =G52*(1+INDEX(Settings!$J$13:$J$16,MATCH(C53,Settings!$A$13:$A$16,0)))+D53
A54: 50 | B54: =Dashboard!$C$5+(50-1)/12 | C54: =INDEX(Dashboard!$C$14:$C$21,MIN(8,INT((50-1)/60)+1)) | D54: =MIN(Dashboard!$C$9,INDEX(Settings!$B$19:$B$58,MIN(40,INT((50-1)/12)+1))) | E54: =E53*(1+INDEX(Settings!$E$13:$E$16,MATCH(C54,Settings!$A$13:$A$16,0)))+D54 | F54: =F53*(1+INDEX(Settings!$I$13:$I$16,MATCH(C54,Settings!$A$13:$A$16,0)))+D54 | G54: =G53*(1+INDEX(Settings!$J$13:$J$16,MATCH(C54,Settings!$A$13:$A$16,0)))+D54
A55: 51 | B55: =Dashboard!$C$5+(51-1)/12 | C55: =INDEX(Dashboard!$C$14:$C$21,MIN(8,INT((51-1)/60)+1)) | D55: =MIN(Dashboard!$C$9,INDEX(Settings!$B$19:$B$58,MIN(40,INT((51-1)/12)+1))) | E55: =E54*(1+INDEX(Settings!$E$13:$E$16,MATCH(C55,Settings!$A$13:$A$16,0)))+D55 | F55: =F54*(1+INDEX(Settings!$I$13:$I$16,MATCH(C55,Settings!$A$13:$A$16,0)))+D55 | G55: =G54*(1+INDEX(Settings!$J$13:$J$16,MATCH(C55,Settings!$A$13:$A$16,0)))+D55
A56: 52 | B56: =Dashboard!$C$5+(52-1)/12 | C56: =INDEX(Dashboard!$C$14:$C$21,MIN(8,INT((52-1)/60)+1)) | D56: =MIN(Dashboard!$C$9,INDEX(Settings!$B$19:$B$58,MIN(40,INT((52-1)/12)+1))) | E56: =E55*(1+INDEX(Settings!$E$13:$E$16,MATCH(C56,Settings!$A$13:$A$16,0)))+D56 | F56: =F55*(1+INDEX(Settings!$I$13:$I$16,MATCH(C56,Settings!$A$13:$A$16,0)))+D56 | G56: =G55*(1+INDEX(Settings!$J$13:$J$16,MATCH(C56,Settings!$A$13:$A$16,0)))+D56
A57: 53 | B57: =Dashboard!$C$5+(53-1)/12 | C57: =INDEX(Dashboard!$C$14:$C$21,MIN(8,INT((53-1)/60)+1)) | D57: =MIN(Dashboard!$C$9,INDEX(Settings!$B$19:$B$58,MIN(40,INT((53-1)/12)+1))) | E57: =E56*(1+INDEX(Settings!$E$13:$E$16,MATCH(C57,Settings!$A$13:$A$16,0)))+D57 | F57: =F56*(1+INDEX(Settings!$I$13:$I$16,MATCH(C57,Settings!$A$13:$A$16,0)))+D57 | G57: =G56*(1+INDEX(Settings!$J$13:$J$16,MATCH(C57,Settings!$A$13:$A$16,0)))+D57
A58: 54 | B58: =Dashboard!$C$5+(54-1)/12 | C58: =INDEX(Dashboard!$C$14:$C$21,MIN(8,INT((54-1)/60)+1)) | D58: =MIN(Dashboard!$C$9,INDEX(Settings!$B$19:$B$58,MIN(40,INT((54-1)/12)+1))) | E58: =E57*(1+INDEX(Settings!$E$13:$E$16,MATCH(C58,Settings!$A$13:$A$16,0)))+D58 | F58: =F57*(1+INDEX(Settings!$I$13:$I$16,MATCH(C58,Settings!$A$13:$A$16,0)))+D58 | G58: =G57*(1+INDEX(Settings!$J$13:$J$16,MATCH(C58,Settings!$A$13:$A$16,0)))+D58
A59: 55 | B59: =Dashboard!$C$5+(55-1)/12 | C59: =INDEX(Dashboard!$C$14:$C$21,MIN(8,INT((55-1)/60)+1)) | D59: =MIN(Dashboard!$C$9,INDEX(Settings!$B$19:$B$58,MIN(40,INT((55-1)/12)+1))) | E59: =E58*(1+INDEX(Settings!$E$13:$E$16,MATCH(C59,Settings!$A$13:$A$16,0)))+D59 | F59: =F58*(1+INDEX(Settings!$I$13:$I$16,MATCH(C59,Settings!$A$13:$A$16,0)))+D59 | G59: =G58*(1+INDEX(Settings!$J$13:$J$16,MATCH(C59,Settings!$A$13:$A$16,0)))+D59
A60: 56 | B60: =Dashboard!$C$5+(56-1)/12 | C60: =INDEX(Dashboard!$C$14:$C$21,MIN(8,INT((56-1)/60)+1)) | D60: =MIN(Dashboard!$C$9,INDEX(Settings!$B$19:$B$58,MIN(40,INT((56-1)/12)+1))) | E60: =E59*(1+INDEX(Settings!$E$13:$E$16,MATCH(C60,Settings!$A$13:$A$16,0)))+D60 | F60: =F59*(1+INDEX(Settings!$I$13:$I$16,MATCH(C60,Settings!$A$13:$A$16,0)))+D60 | G60: =G59*(1+INDEX(Settings!$J$13:$J$16,MATCH(C60,Settings!$A$13:$A$16,0)))+D60
A61: 57 | B61: =Dashboard!$C$5+(57-1)/12 | C61: =INDEX(Dashboard!$C$14:$C$21,MIN(8,INT((57-1)/60)+1)) | D61: =MIN(Dashboard!$C$9,INDEX(Settings!$B$19:$B$58,MIN(40,INT((57-1)/12)+1))) | E61: =E60*(1+INDEX(Settings!$E$13:$E$16,MATCH(C61,Settings!$A$13:$A$16,0)))+D61 | F61: =F60*(1+INDEX(Settings!$I$13:$I$16,MATCH(C61,Settings!$A$13:$A$16,0)))+D61 | G61: =G60*(1+INDEX(Settings!$J$13:$J$16,MATCH(C61,Settings!$A$13:$A$16,0)))+D61
A62: 58 | B62: =Dashboard!$C$5+(58-1)/12 | C62: =INDEX(Dashboard!$C$14:$C$21,MIN(8,INT((58-1)/60)+1)) | D62: =MIN(Dashboard!$C$9,INDEX(Settings!$B$19:$B$58,MIN(40,INT((58-1)/12)+1))) | E62: =E61*(1+INDEX(Settings!$E$13:$E$16,MATCH(C62,Settings!$A$13:$A$16,0)))+D62 | F62: =F61*(1+INDEX(Settings!$I$13:$I$16,MATCH(C62,Settings!$A$13:$A$16,0)))+D62 | G62: =G61*(1+INDEX(Settings!$J$13:$J$16,MATCH(C62,Settings!$A$13:$A$16,0)))+D62
A63: 59 | B63: =Dashboard!$C$5+(59-1)/12 | C63: =INDEX(Dashboard!$C$14:$C$21,MIN(8,INT((59-1)/60)+1)) | D63: =MIN(Dashboard!$C$9,INDEX(Settings!$B$19:$B$58,MIN(40,INT((59-1)/12)+1))) | E63: =E62*(1+INDEX(Settings!$E$13:$E$16,MATCH(C63,Settings!$A$13:$A$16,0)))+D63 | F63: =F62*(1+INDEX(Settings!$I$13:$I$16,MATCH(C63,Settings!$A$13:$A$16,0)))+D63 | G63: =G62*(1+INDEX(Settings!$J$13:$J$16,MATCH(C63,Settings!$A$13:$A$16,0)))+D63
A64: 60 | B64: =Dashboard!$C$5+(60-1)/12 | C64: =INDEX(Dashboard!$C$14:$C$21,MIN(8,INT((60-1)/60)+1)) | D64: =MIN(Dashboard!$C$9,INDEX(Settings!$B$19:$B$58,MIN(40,INT((60-1)/12)+1))) | E64: =E63*(1+INDEX(Settings!$E$13:$E$16,MATCH(C64,Settings!$A$13:$A$16,0)))+D64 | F64: =F63*(1+INDEX(Settings!$I$13:$I$16,MATCH(C64,Settings!$A$13:$A$16,0)))+D64 | G64: =G63*(1+INDEX(Settings!$J$13:$J$16,MATCH(C64,Settings!$A$13:$A$16,0)))+D64
A65: 61 | B65: =Dashboard!$C$5+(61-1)/12 | C65: =INDEX(Dashboard!$C$14:$C$21,MIN(8,INT((61-1)/60)+1)) | D65: =MIN(Dashboard!$C$9,INDEX(Settings!$B$19:$B$58,MIN(40,INT((61-1)/12)+1))) | E65: =E64*(1+INDEX(Settings!$E$13:$E$16,MATCH(C65,Settings!$A$13:$A$16,0)))+D65 | F65: =F64*(1+INDEX(Settings!$I$13:$I$16,MATCH(C65,Settings!$A$13:$A$16,0)))+D65 | G65: =G64*(1+INDEX(Settings!$J$13:$J$16,MATCH(C65,Settings!$A$13:$A$16,0)))+D65
A66: 62 | B66: =Dashboard!$C$5+(62-1)/12 | C66: =INDEX(Dashboard!$C$14:$C$21,MIN(8,INT((62-1)/60)+1)) | D66: =MIN(Dashboard!$C$9,INDEX(Settings!$B$19:$B$58,MIN(40,INT((62-1)/12)+1))) | E66: =E65*(1+INDEX(Settings!$E$13:$E$16,MATCH(C66,Settings!$A$13:$A$16,0)))+D66 | F66: =F65*(1+INDEX(Settings!$I$13:$I$16,MATCH(C66,Settings!$A$13:$A$16,0)))+D66 | G66: =G65*(1+INDEX(Settings!$J$13:$J$16,MATCH(C66,Settings!$A$13:$A$16,0)))+D66
A67: 63 | B67: =Dashboard!$C$5+(63-1)/12 | C67: =INDEX(Dashboard!$C$14:$C$21,MIN(8,INT((63-1)/60)+1)) | D67: =MIN(Dashboard!$C$9,INDEX(Settings!$B$19:$B$58,MIN(40,INT((63-1)/12)+1))) | E67: =E66*(1+INDEX(Settings!$E$13:$E$16,MATCH(C67,Settings!$A$13:$A$16,0)))+D67 | F67: =F66*(1+INDEX(Settings!$I$13:$I$16,MATCH(C67,Settings!$A$13:$A$16,0)))+D67 | G67: =G66*(1+INDEX(Settings!$J$13:$J$16,MATCH(C67,Settings!$A$13:$A$16,0)))+D67
A68: 64 | B68: =Dashboard!$C$5+(64-1)/12 | C68: =INDEX(Dashboard!$C$14:$C$21,MIN(8,INT((64-1)/60)+1)) | D68: =MIN(Dashboard!$C$9,INDEX(Settings!$B$19:$B$58,MIN(40,INT((64-1)/12)+1))) | E68: =E67*(1+INDEX(Settings!$E$13:$E$16,MATCH(C68,Settings!$A$13:$A$16,0)))+D68 | F68: =F67*(1+INDEX(Settings!$I$13:$I$16,MATCH(C68,Settings!$A$13:$A$16,0)))+D68 | G68: =G67*(1+INDEX(Settings!$J$13:$J$16,MATCH(C68,Settings!$A$13:$A$16,0)))+D68
A69: 65 | B69: =Dashboard!$C$5+(65-1)/12 | C69: =INDEX(Dashboard!$C$14:$C$21,MIN(8,INT((65-1)/60)+1)) | D69: =MIN(Dashboard!$C$9,INDEX(Settings!$B$19:$B$58,MIN(40,INT((65-1)/12)+1))) | E69: =E68*(1+INDEX(Settings!$E$13:$E$16,MATCH(C69,Settings!$A$13:$A$16,0)))+D69 | F69: =F68*(1+INDEX(Settings!$I$13:$I$16,MATCH(C69,Settings!$A$13:$A$16,0)))+D69 | G69: =G68*(1+INDEX(Settings!$J$13:$J$16,MATCH(C69,Settings!$A$13:$A$16,0)))+D69
A70: 66 | B70: =Dashboard!$C$5+(66-1)/12 | C70: =INDEX(Dashboard!$C$14:$C$21,MIN(8,INT((66-1)/60)+1)) | D70: =MIN(Dashboard!$C$9,INDEX(Settings!$B$19:$B$58,MIN(40,INT((66-1)/12)+1))) | E70: =E69*(1+INDEX(Settings!$E$13:$E$16,MATCH(C70,Settings!$A$13:$A$16,0)))+D70 | F70: =F69*(1+INDEX(Settings!$I$13:$I$16,MATCH(C70,Settings!$A$13:$A$16,0)))+D70 | G70: =G69*(1+INDEX(Settings!$J$13:$J$16,MATCH(C70,Settings!$A$13:$A$16,0)))+D70
A71: 67 | B71: =Dashboard!$C$5+(67-1)/12 | C71: =INDEX(Dashboard!$C$14:$C$21,MIN(8,INT((67-1)/60)+1)) | D71: =MIN(Dashboard!$C$9,INDEX(Settings!$B$19:$B$58,MIN(40,INT((67-1)/12)+1))) | E71: =E70*(1+INDEX(Settings!$E$13:$E$16,MATCH(C71,Settings!$A$13:$A$16,0)))+D71 | F71: =F70*(1+INDEX(Settings!$I$13:$I$16,MATCH(C71,Settings!$A$13:$A$16,0)))+D71 | G71: =G70*(1+INDEX(Settings!$J$13:$J$16,MATCH(C71,Settings!$A$13:$A$16,0)))+D71
A72: 68 | B72: =Dashboard!$C$5+(68-1)/12 | C72: =INDEX(Dashboard!$C$14:$C$21,MIN(8,INT((68-1)/60)+1)) | D72: =MIN(Dashboard!$C$9,INDEX(Settings!$B$19:$B$58,MIN(40,INT((68-1)/12)+1))) | E72: =E71*(1+INDEX(Settings!$E$13:$E$16,MATCH(C72,Settings!$A$13:$A$16,0)))+D72 | F72: =F71*(1+INDEX(Settings!$I$13:$I$16,MATCH(C72,Settings!$A$13:$A$16,0)))+D72 | G72: =G71*(1+INDEX(Settings!$J$13:$J$16,MATCH(C72,Settings!$A$13:$A$16,0)))+D72
A73: 69 | B73: =Dashboard!$C$5+(69-1)/12 | C73: =INDEX(Dashboard!$C$14:$C$21,MIN(8,INT((69-1)/60)+1)) | D73: =MIN(Dashboard!$C$9,INDEX(Settings!$B$19:$B$58,MIN(40,INT((69-1)/12)+1))) | E73: =E72*(1+INDEX(Settings!$E$13:$E$16,MATCH(C73,Settings!$A$13:$A$16,0)))+D73 | F73: =F72*(1+INDEX(Settings!$I$13:$I$16,MATCH(C73,Settings!$A$13:$A$16,0)))+D73 | G73: =G72*(1+INDEX(Settings!$J$13:$J$16,MATCH(C73,Settings!$A$13:$A$16,0)))+D73
A74: 70 | B74: =Dashboard!$C$5+(70-1)/12 | C74: =INDEX(Dashboard!$C$14:$C$21,MIN(8,INT((70-1)/60)+1)) | D74: =MIN(Dashboard!$C$9,INDEX(Settings!$B$19:$B$58,MIN(40,INT((70-1)/12)+1))) | E74: =E73*(1+INDEX(Settings!$E$13:$E$16,MATCH(C74,Settings!$A$13:$A$16,0)))+D74 | F74: =F73*(1+INDEX(Settings!$I$13:$I$16,MATCH(C74,Settings!$A$13:$A$16,0)))+D74 | G74: =G73*(1+INDEX(Settings!$J$13:$J$16,MATCH(C74,Settings!$A$13:$A$16,0)))+D74
A75: 71 | B75: =Dashboard!$C$5+(71-1)/12 | C75: =INDEX(Dashboard!$C$14:$C$21,MIN(8,INT((71-1)/60)+1)) | D75: =MIN(Dashboard!$C$9,INDEX(Settings!$B$19:$B$58,MIN(40,INT((71-1)/12)+1))) | E75: =E74*(1+INDEX(Settings!$E$13:$E$16,MATCH(C75,Settings!$A$13:$A$16,0)))+D75 | F75: =F74*(1+INDEX(Settings!$I$13:$I$16,MATCH(C75,Settings!$A$13:$A$16,0)))+D75 | G75: =G74*(1+INDEX(Settings!$J$13:$J$16,MATCH(C75,Settings!$A$13:$A$16,0)))+D75
A76: 72 | B76: =Dashboard!$C$5+(72-1)/12 | C76: =INDEX(Dashboard!$C$14:$C$21,MIN(8,INT((72-1)/60)+1)) | D76: =MIN(Dashboard!$C$9,INDEX(Settings!$B$19:$B$58,MIN(40,INT((72-1)/12)+1))) | E76: =E75*(1+INDEX(Settings!$E$13:$E$16,MATCH(C76,Settings!$A$13:$A$16,0)))+D76 | F76: =F75*(1+INDEX(Settings!$I$13:$I$16,MATCH(C76,Settings!$A$13:$A$16,0)))+D76 | G76: =G75*(1+INDEX(Settings!$J$13:$J$16,MATCH(C76,Settings!$A$13:$A$16,0)))+D76
A77: 73 | B77: =Dashboard!$C$5+(73-1)/12 | C77: =INDEX(Dashboard!$C$14:$C$21,MIN(8,INT((73-1)/60)+1)) | D77: =MIN(Dashboard!$C$9,INDEX(Settings!$B$19:$B$58,MIN(40,INT((73-1)/12)+1))) | E77: =E76*(1+INDEX(Settings!$E$13:$E$16,MATCH(C77,Settings!$A$13:$A$16,0)))+D77 | F77: =F76*(1+INDEX(Settings!$I$13:$I$16,MATCH(C77,Settings!$A$13:$A$16,0)))+D77 | G77: =G76*(1+INDEX(Settings!$J$13:$J$16,MATCH(C77,Settings!$A$13:$A$16,0)))+D77
A78: 74 | B78: =Dashboard!$C$5+(74-1)/12 | C78: =INDEX(Dashboard!$C$14:$C$21,MIN(8,INT((74-1)/60)+1)) | D78: =MIN(Dashboard!$C$9,INDEX(Settings!$B$19:$B$58,MIN(40,INT((74-1)/12)+1))) | E78: =E77*(1+INDEX(Settings!$E$13:$E$16,MATCH(C78,Settings!$A$13:$A$16,0)))+D78 | F78: =F77*(1+INDEX(Settings!$I$13:$I$16,MATCH(C78,Settings!$A$13:$A$16,0)))+D78 | G78: =G77*(1+INDEX(Settings!$J$13:$J$16,MATCH(C78,Settings!$A$13:$A$16,0)))+D78
A79: 75 | B79: =Dashboard!$C$5+(75-1)/12 | C79: =INDEX(Dashboard!$C$14:$C$21,MIN(8,INT((75-1)/60)+1)) | D79: =MIN(Dashboard!$C$9,INDEX(Settings!$B$19:$B$58,MIN(40,INT((75-1)/12)+1))) | E79: =E78*(1+INDEX(Settings!$E$13:$E$16,MATCH(C79,Settings!$A$13:$A$16,0)))+D79 | F79: =F78*(1+INDEX(Settings!$I$13:$I$16,MATCH(C79,Settings!$A$13:$A$16,0)))+D79 | G79: =G78*(1+INDEX(Settings!$J$13:$J$16,MATCH(C79,Settings!$A$13:$A$16,0)))+D79
A80: 76 | B80: =Dashboard!$C$5+(76-1)/12 | C80: =INDEX(Dashboard!$C$14:$C$21,MIN(8,INT((76-1)/60)+1)) | D80: =MIN(Dashboard!$C$9,INDEX(Settings!$B$19:$B$58,MIN(40,INT((76-1)/12)+1))) | E80: =E79*(1+INDEX(Settings!$E$13:$E$16,MATCH(C80,Settings!$A$13:$A$16,0)))+D80 | F80: =F79*(1+INDEX(Settings!$I$13:$I$16,MATCH(C80,Settings!$A$13:$A$16,0)))+D80 | G80: =G79*(1+INDEX(Settings!$J$13:$J$16,MATCH(C80,Settings!$A$13:$A$16,0)))+D80
A81: 77 | B81: =Dashboard!$C$5+(77-1)/12 | C81: =INDEX(Dashboard!$C$14:$C$21,MIN(8,INT((77-1)/60)+1)) | D81: =MIN(Dashboard!$C$9,INDEX(Settings!$B$19:$B$58,MIN(40,INT((77-1)/12)+1))) | E81: =E80*(1+INDEX(Settings!$E$13:$E$16,MATCH(C81,Settings!$A$13:$A$16,0)))+D81 | F81: =F80*(1+INDEX(Settings!$I$13:$I$16,MATCH(C81,Settings!$A$13:$A$16,0)))+D81 | G81: =G80*(1+INDEX(Settings!$J$13:$J$16,MATCH(C81,Settings!$A$13:$A$16,0)))+D81
A82: 78 | B82: =Dashboard!$C$5+(78-1)/12 | C82: =INDEX(Dashboard!$C$14:$C$21,MIN(8,INT((78-1)/60)+1)) | D82: =MIN(Dashboard!$C$9,INDEX(Settings!$B$19:$B$58,MIN(40,INT((78-1)/12)+1))) | E82: =E81*(1+INDEX(Settings!$E$13:$E$16,MATCH(C82,Settings!$A$13:$A$16,0)))+D82 | F82: =F81*(1+INDEX(Settings!$I$13:$I$16,MATCH(C82,Settings!$A$13:$A$16,0)))+D82 | G82: =G81*(1+INDEX(Settings!$J$13:$J$16,MATCH(C82,Settings!$A$13:$A$16,0)))+D82
A83: 79 | B83: =Dashboard!$C$5+(79-1)/12 | C83: =INDEX(Dashboard!$C$14:$C$21,MIN(8,INT((79-1)/60)+1)) | D83: =MIN(Dashboard!$C$9,INDEX(Settings!$B$19:$B$58,MIN(40,INT((79-1)/12)+1))) | E83: =E82*(1+INDEX(Settings!$E$13:$E$16,MATCH(C83,Settings!$A$13:$A$16,0)))+D83 | F83: =F82*(1+INDEX(Settings!$I$13:$I$16,MATCH(C83,Settings!$A$13:$A$16,0)))+D83 | G83: =G82*(1+INDEX(Settings!$J$13:$J$16,MATCH(C83,Settings!$A$13:$A$16,0)))+D83
A84: 80 | B84: =Dashboard!$C$5+(80-1)/12 | C84: =INDEX(Dashboard!$C$14:$C$21,MIN(8,INT((80-1)/60)+1)) | D84: =MIN(Dashboard!$C$9,INDEX(Settings!$B$19:$B$58,MIN(40,INT((80-1)/12)+1))) | E84: =E83*(1+INDEX(Settings!$E$13:$E$16,MATCH(C84,Settings!$A$13:$A$16,0)))+D84 | F84: =F83*(1+INDEX(Settings!$I$13:$I$16,MATCH(C84,Settings!$A$13:$A$16,0)))+D84 | G84: =G83*(1+INDEX(Settings!$J$13:$J$16,MATCH(C84,Settings!$A$13:$A$16,0)))+D84
A85: 81 | B85: =Dashboard!$C$5+(81-1)/12 | C85: =INDEX(Dashboard!$C$14:$C$21,MIN(8,INT((81-1)/60)+1)) | D85: =MIN(Dashboard!$C$9,INDEX(Settings!$B$19:$B$58,MIN(40,INT((81-1)/12)+1))) | E85: =E84*(1+INDEX(Settings!$E$13:$E$16,MATCH(C85,Settings!$A$13:$A$16,0)))+D85 | F85: =F84*(1+INDEX(Settings!$I$13:$I$16,MATCH(C85,Settings!$A$13:$A$16,0)))+D85 | G85: =G84*(1+INDEX(Settings!$J$13:$J$16,MATCH(C85,Settings!$A$13:$A$16,0)))+D85
A86: 82 | B86: =Dashboard!$C$5+(82-1)/12 | C86: =INDEX(Dashboard!$C$14:$C$21,MIN(8,INT((82-1)/60)+1)) | D86: =MIN(Dashboard!$C$9,INDEX(Settings!$B$19:$B$58,MIN(40,INT((82-1)/12)+1))) | E86: =E85*(1+INDEX(Settings!$E$13:$E$16,MATCH(C86,Settings!$A$13:$A$16,0)))+D86 | F86: =F85*(1+INDEX(Settings!$I$13:$I$16,MATCH(C86,Settings!$A$13:$A$16,0)))+D86 | G86: =G85*(1+INDEX(Settings!$J$13:$J$16,MATCH(C86,Settings!$A$13:$A$16,0)))+D86
A87: 83 | B87: =Dashboard!$C$5+(83-1)/12 | C87: =INDEX(Dashboard!$C$14:$C$21,MIN(8,INT((83-1)/60)+1)) | D87: =MIN(Dashboard!$C$9,INDEX(Settings!$B$19:$B$58,MIN(40,INT((83-1)/12)+1))) | E87: =E86*(1+INDEX(Settings!$E$13:$E$16,MATCH(C87,Settings!$A$13:$A$16,0)))+D87 | F87: =F86*(1+INDEX(Settings!$I$13:$I$16,MATCH(C87,Settings!$A$13:$A$16,0)))+D87 | G87: =G86*(1+INDEX(Settings!$J$13:$J$16,MATCH(C87,Settings!$A$13:$A$16,0)))+D87
A88: 84 | B88: =Dashboard!$C$5+(84-1)/12 | C88: =INDEX(Dashboard!$C$14:$C$21,MIN(8,INT((84-1)/60)+1)) | D88: =MIN(Dashboard!$C$9,INDEX(Settings!$B$19:$B$58,MIN(40,INT((84-1)/12)+1))) | E88: =E87*(1+INDEX(Settings!$E$13:$E$16,MATCH(C88,Settings!$A$13:$A$16,0)))+D88 | F88: =F87*(1+INDEX(Settings!$I$13:$I$16,MATCH(C88,Settings!$A$13:$A$16,0)))+D88 | G88: =G87*(1+INDEX(Settings!$J$13:$J$16,MATCH(C88,Settings!$A$13:$A$16,0)))+D88
A89: 85 | B89: =Dashboard!$C$5+(85-1)/12 | C89: =INDEX(Dashboard!$C$14:$C$21,MIN(8,INT((85-1)/60)+1)) | D89: =MIN(Dashboard!$C$9,INDEX(Settings!$B$19:$B$58,MIN(40,INT((85-1)/12)+1))) | E89: =E88*(1+INDEX(Settings!$E$13:$E$16,MATCH(C89,Settings!$A$13:$A$16,0)))+D89 | F89: =F88*(1+INDEX(Settings!$I$13:$I$16,MATCH(C89,Settings!$A$13:$A$16,0)))+D89 | G89: =G88*(1+INDEX(Settings!$J$13:$J$16,MATCH(C89,Settings!$A$13:$A$16,0)))+D89
A90: 86 | B90: =Dashboard!$C$5+(86-1)/12 | C90: =INDEX(Dashboard!$C$14:$C$21,MIN(8,INT((86-1)/60)+1)) | D90: =MIN(Dashboard!$C$9,INDEX(Settings!$B$19:$B$58,MIN(40,INT((86-1)/12)+1))) | E90: =E89*(1+INDEX(Settings!$E$13:$E$16,MATCH(C90,Settings!$A$13:$A$16,0)))+D90 | F90: =F89*(1+INDEX(Settings!$I$13:$I$16,MATCH(C90,Settings!$A$13:$A$16,0)))+D90 | G90: =G89*(1+INDEX(Settings!$J$13:$J$16,MATCH(C90,Settings!$A$13:$A$16,0)))+D90
A91: 87 | B91: =Dashboard!$C$5+(87-1)/12 | C91: =INDEX(Dashboard!$C$14:$C$21,MIN(8,INT((87-1)/60)+1)) | D91: =MIN(Dashboard!$C$9,INDEX(Settings!$B$19:$B$58,MIN(40,INT((87-1)/12)+1))) | E91: =E90*(1+INDEX(Settings!$E$13:$E$16,MATCH(C91,Settings!$A$13:$A$16,0)))+D91 | F91: =F90*(1+INDEX(Settings!$I$13:$I$16,MATCH(C91,Settings!$A$13:$A$16,0)))+D91 | G91: =G90*(1+INDEX(Settings!$J$13:$J$16,MATCH(C91,Settings!$A$13:$A$16,0)))+D91
A92: 88 | B92: =Dashboard!$C$5+(88-1)/12 | C92: =INDEX(Dashboard!$C$14:$C$21,MIN(8,INT((88-1)/60)+1)) | D92: =MIN(Dashboard!$C$9,INDEX(Settings!$B$19:$B$58,MIN(40,INT((88-1)/12)+1))) | E92: =E91*(1+INDEX(Settings!$E$13:$E$16,MATCH(C92,Settings!$A$13:$A$16,0)))+D92 | F92: =F91*(1+INDEX(Settings!$I$13:$I$16,MATCH(C92,Settings!$A$13:$A$16,0)))+D92 | G92: =G91*(1+INDEX(Settings!$J$13:$J$16,MATCH(C92,Settings!$A$13:$A$16,0)))+D92
A93: 89 | B93: =Dashboard!$C$5+(89-1)/12 | C93: =INDEX(Dashboard!$C$14:$C$21,MIN(8,INT((89-1)/60)+1)) | D93: =MIN(Dashboard!$C$9,INDEX(Settings!$B$19:$B$58,MIN(40,INT((89-1)/12)+1))) | E93: =E92*(1+INDEX(Settings!$E$13:$E$16,MATCH(C93,Settings!$A$13:$A$16,0)))+D93 | F93: =F92*(1+INDEX(Settings!$I$13:$I$16,MATCH(C93,Settings!$A$13:$A$16,0)))+D93 | G93: =G92*(1+INDEX(Settings!$J$13:$J$16,MATCH(C93,Settings!$A$13:$A$16,0)))+D93
A94: 90 | B94: =Dashboard!$C$5+(90-1)/12 | C94: =INDEX(Dashboard!$C$14:$C$21,MIN(8,INT((90-1)/60)+1)) | D94: =MIN(Dashboard!$C$9,INDEX(Settings!$B$19:$B$58,MIN(40,INT((90-1)/12)+1))) | E94: =E93*(1+INDEX(Settings!$E$13:$E$16,MATCH(C94,Settings!$A$13:$A$16,0)))+D94 | F94: =F93*(1+INDEX(Settings!$I$13:$I$16,MATCH(C94,Settings!$A$13:$A$16,0)))+D94 | G94: =G93*(1+INDEX(Settings!$J$13:$J$16,MATCH(C94,Settings!$A$13:$A$16,0)))+D94
A95: 91 | B95: =Dashboard!$C$5+(91-1)/12 | C95: =INDEX(Dashboard!$C$14:$C$21,MIN(8,INT((91-1)/60)+1)) | D95: =MIN(Dashboard!$C$9,INDEX(Settings!$B$19:$B$58,MIN(40,INT((91-1)/12)+1))) | E95: =E94*(1+INDEX(Settings!$E$13:$E$16,MATCH(C95,Settings!$A$13:$A$16,0)))+D95 | F95: =F94*(1+INDEX(Settings!$I$13:$I$16,MATCH(C95,Settings!$A$13:$A$16,0)))+D95 | G95: =G94*(1+INDEX(Settings!$J$13:$J$16,MATCH(C95,Settings!$A$13:$A$16,0)))+D95
A96: 92 | B96: =Dashboard!$C$5+(92-1)/12 | C96: =INDEX(Dashboard!$C$14:$C$21,MIN(8,INT((92-1)/60)+1)) | D96: =MIN(Dashboard!$C$9,INDEX(Settings!$B$19:$B$58,MIN(40,INT((92-1)/12)+1))) | E96: =E95*(1+INDEX(Settings!$E$13:$E$16,MATCH(C96,Settings!$A$13:$A$16,0)))+D96 | F96: =F95*(1+INDEX(Settings!$I$13:$I$16,MATCH(C96,Settings!$A$13:$A$16,0)))+D96 | G96: =G95*(1+INDEX(Settings!$J$13:$J$16,MATCH(C96,Settings!$A$13:$A$16,0)))+D96
A97: 93 | B97: =Dashboard!$C$5+(93-1)/12 | C97: =INDEX(Dashboard!$C$14:$C$21,MIN(8,INT((93-1)/60)+1)) | D97: =MIN(Dashboard!$C$9,INDEX(Settings!$B$19:$B$58,MIN(40,INT((93-1)/12)+1))) | E97: =E96*(1+INDEX(Settings!$E$13:$E$16,MATCH(C97,Settings!$A$13:$A$16,0)))+D97 | F97: =F96*(1+INDEX(Settings!$I$13:$I$16,MATCH(C97,Settings!$A$13:$A$16,0)))+D97 | G97: =G96*(1+INDEX(Settings!$J$13:$J$16,MATCH(C97,Settings!$A$13:$A$16,0)))+D97
A98: 94 | B98: =Dashboard!$C$5+(94-1)/12 | C98: =INDEX(Dashboard!$C$14:$C$21,MIN(8,INT((94-1)/60)+1)) | D98: =MIN(Dashboard!$C$9,INDEX(Settings!$B$19:$B$58,MIN(40,INT((94-1)/12)+1))) | E98: =E97*(1+INDEX(Settings!$E$13:$E$16,MATCH(C98,Settings!$A$13:$A$16,0)))+D98 | F98: =F97*(1+INDEX(Settings!$I$13:$I$16,MATCH(C98,Settings!$A$13:$A$16,0)))+D98 | G98: =G97*(1+INDEX(Settings!$J$13:$J$16,MATCH(C98,Settings!$A$13:$A$16,0)))+D98
A99: 95 | B99: =Dashboard!$C$5+(95-1)/12 | C99: =INDEX(Dashboard!$C$14:$C$21,MIN(8,INT((95-1)/60)+1)) | D99: =MIN(Dashboard!$C$9,INDEX(Settings!$B$19:$B$58,MIN(40,INT((95-1)/12)+1))) | E99: =E98*(1+INDEX(Settings!$E$13:$E$16,MATCH(C99,Settings!$A$13:$A$16,0)))+D99 | F99: =F98*(1+INDEX(Settings!$I$13:$I$16,MATCH(C99,Settings!$A$13:$A$16,0)))+D99 | G99: =G98*(1+INDEX(Settings!$J$13:$J$16,MATCH(C99,Settings!$A$13:$A$16,0)))+D99
A100: 96 | B100: =Dashboard!$C$5+(96-1)/12 | C100: =INDEX(Dashboard!$C$14:$C$21,MIN(8,INT((96-1)/60)+1)) | D100: =MIN(Dashboard!$C$9,INDEX(Settings!$B$19:$B$58,MIN(40,INT((96-1)/12)+1))) | E100: =E99*(1+INDEX(Settings!$E$13:$E$16,MATCH(C100,Settings!$A$13:$A$16,0)))+D100 | F100: =F99*(1+INDEX(Settings!$I$13:$I$16,MATCH(C100,Settings!$A$13:$A$16,0)))+D100 | G100: =G99*(1+INDEX(Settings!$J$13:$J$16,MATCH(C100,Settings!$A$13:$A$16,0)))+D100
A101: 97 | B101: =Dashboard!$C$5+(97-1)/12 | C101: =INDEX(Dashboard!$C$14:$C$21,MIN(8,INT((97-1)/60)+1)) | D101: =MIN(Dashboard!$C$9,INDEX(Settings!$B$19:$B$58,MIN(40,INT((97-1)/12)+1))) | E101: =E100*(1+INDEX(Settings!$E$13:$E$16,MATCH(C101,Settings!$A$13:$A$16,0)))+D101 | F101: =F100*(1+INDEX(Settings!$I$13:$I$16,MATCH(C101,Settings!$A$13:$A$16,0)))+D101 | G101: =G100*(1+INDEX(Settings!$J$13:$J$16,MATCH(C101,Settings!$A$13:$A$16,0)))+D101
...

Sheet Settings
A1: Advanced Settings
A2: Regime mix, frictions, contribution schedule, and the per-tier return engine. Yellow = edit.
A4: Expected regime mix (share of time)
B5: Growth | C5: Reflation | D5: Stagflation | E5: Deflation
A6: Weight | B6: 0.32 | C6: 0.47 | D6: 0.08 | E6: 0.13 | F6: =SUM(B6:E6) | G6: =IF(ABS(F6-1)>0.005,"← must sum to 100%","")
A8: Regime-switch cost drag (bps / yr) | B8: 60
A9: Horizon (years, from Dashboard ages) | B9: =Dashboard!$C$6-Dashboard!$C$5
A10: Backtest return haircut (%) | B10: =Dashboard!$C$10
A11: Per-tier return engine (derived — do not edit)
A12: Tier | B12: Mean monthly | C12: Annual (pre-tax) | D12: After-tax annual | E12: Net monthly | F12: Monthly sd | G12: Annual sd | H12: S.E. (avg) | I12: Low monthly | J12: High monthly
A13: CONS | B13: =(SUMPRODUCT($B$6:$E$6,Data!$B$6:$E$6)-$B$8/10000/12)*(1-$B$10) | C13: =(1+B13)^12-1 | D13: =IF(C13>0,C13*(1-Dashboard!$C$11),C13) | E13: =(1+D13)^(1/12)-1 | F13: =SUMPRODUCT($B$6:$E$6,Data!$B$13:$E$13) | G13: =F13*SQRT(12) | H13: =G13/SQRT(MAX(1,$B$9)) | I13: =(1+D13-H13)^(1/12)-1 | J13: =(1+D13+H13)^(1/12)-1
A14: MOD | B14: =(SUMPRODUCT($B$6:$E$6,Data!$B$7:$E$7)-$B$8/10000/12)*(1-$B$10) | C14: =(1+B14)^12-1 | D14: =IF(C14>0,C14*(1-Dashboard!$C$11),C14) | E14: =(1+D14)^(1/12)-1 | F14: =SUMPRODUCT($B$6:$E$6,Data!$B$14:$E$14) | G14: =F14*SQRT(12) | H14: =G14/SQRT(MAX(1,$B$9)) | I14: =(1+D14-H14)^(1/12)-1 | J14: =(1+D14+H14)^(1/12)-1
A15: AGG | B15: =(SUMPRODUCT($B$6:$E$6,Data!$B$8:$E$8)-$B$8/10000/12)*(1-$B$10) | C15: =(1+B15)^12-1 | D15: =IF(C15>0,C15*(1-Dashboard!$C$11),C15) | E15: =(1+D15)^(1/12)-1 | F15: =SUMPRODUCT($B$6:$E$6,Data!$B$15:$E$15) | G15: =F15*SQRT(12) | H15: =G15/SQRT(MAX(1,$B$9)) | I15: =(1+D15-H15)^(1/12)-1 | J15: =(1+D15+H15)^(1/12)-1
A16: VAGG | B16: =(SUMPRODUCT($B$6:$E$6,Data!$B$9:$E$9)-$B$8/10000/12)*(1-$B$10) | C16: =(1+B16)^12-1 | D16: =IF(C16>0,C16*(1-Dashboard!$C$11),C16) | E16: =(1+D16)^(1/12)-1 | F16: =SUMPRODUCT($B$6:$E$6,Data!$B$16:$E$16) | G16: =F16*SQRT(12) | H16: =G16/SQRT(MAX(1,$B$9)) | I16: =(1+D16-H16)^(1/12)-1 | J16: =(1+D16+H16)^(1/12)-1
A18: Contribution schedule — driven by the RAMP STAGES table (edit the yellow rates)
A19: Year 1 | B19: =Dashboard!$C$8 | D19: Ramp stage | E19: From yr | F19: Growth %/yr
A20: Year 2 | B20: =ROUND(B19*(1+INDEX($F$20:$F$32,MATCH(2,$E$20:$E$32,1)))/25,0)*25 | D20: Ages 26-28 | E20: 2 | F20: 0.35
A21: Year 3 | B21: =ROUND(B20*(1+INDEX($F$20:$F$32,MATCH(3,$E$20:$E$32,1)))/25,0)*25 | D21: Ages 29-31 | E21: 5 | F21: 0.15
A22: Year 4 | B22: =ROUND(B21*(1+INDEX($F$20:$F$32,MATCH(4,$E$20:$E$32,1)))/25,0)*25 | D22: Ages 32-34 | E22: 8 | F22: 0.1
A23: Year 5 | B23: =ROUND(B22*(1+INDEX($F$20:$F$32,MATCH(5,$E$20:$E$32,1)))/25,0)*25 | D23: Ages 35-37 | E23: 11 | F23: 0.08
A24: Year 6 | B24: =ROUND(B23*(1+INDEX($F$20:$F$32,MATCH(6,$E$20:$E$32,1)))/25,0)*25 | D24: Ages 38-40 | E24: 14 | F24: 0.08
A25: Year 7 | B25: =ROUND(B24*(1+INDEX($F$20:$F$32,MATCH(7,$E$20:$E$32,1)))/25,0)*25 | D25: Ages 41-43 | E25: 17 | F25: 0.07
A26: Year 8 | B26: =ROUND(B25*(1+INDEX($F$20:$F$32,MATCH(8,$E$20:$E$32,1)))/25,0)*25 | D26: Ages 44-46 | E26: 20 | F26: 0.07
A27: Year 9 | B27: =ROUND(B26*(1+INDEX($F$20:$F$32,MATCH(9,$E$20:$E$32,1)))/25,0)*25 | D27: Ages 47-49 | E27: 23 | F27: 0.07
A28: Year 10 | B28: =ROUND(B27*(1+INDEX($F$20:$F$32,MATCH(10,$E$20:$E$32,1)))/25,0)*25 | D28: Ages 50-52 | E28: 26 | F28: 0.06
A29: Year 11 | B29: =ROUND(B28*(1+INDEX($F$20:$F$32,MATCH(11,$E$20:$E$32,1)))/25,0)*25 | D29: Ages 53-55 | E29: 29 | F29: 0.06
A30: Year 12 | B30: =ROUND(B29*(1+INDEX($F$20:$F$32,MATCH(12,$E$20:$E$32,1)))/25,0)*25 | D30: Ages 56-58 | E30: 32 | F30: 0.05
A31: Year 13 | B31: =ROUND(B30*(1+INDEX($F$20:$F$32,MATCH(13,$E$20:$E$32,1)))/25,0)*25 | D31: Ages 59-61 | E31: 35 | F31: 0.05
A32: Year 14 | B32: =ROUND(B31*(1+INDEX($F$20:$F$32,MATCH(14,$E$20:$E$32,1)))/25,0)*25 | D32: Ages 62-64 | E32: 38 | F32: 0.05
A33: Year 15 | B33: =ROUND(B32*(1+INDEX($F$20:$F$32,MATCH(15,$E$20:$E$32,1)))/25,0)*25
A34: Year 16 | B34: =ROUND(B33*(1+INDEX($F$20:$F$32,MATCH(16,$E$20:$E$32,1)))/25,0)*25
A35: Year 17 | B35: =ROUND(B34*(1+INDEX($F$20:$F$32,MATCH(17,$E$20:$E$32,1)))/25,0)*25
A36: Year 18 | B36: =ROUND(B35*(1+INDEX($F$20:$F$32,MATCH(18,$E$20:$E$32,1)))/25,0)*25
A37: Year 19 | B37: =ROUND(B36*(1+INDEX($F$20:$F$32,MATCH(19,$E$20:$E$32,1)))/25,0)*25
A38: Year 20 | B38: =ROUND(B37*(1+INDEX($F$20:$F$32,MATCH(20,$E$20:$E$32,1)))/25,0)*25
A39: Year 21 | B39: =ROUND(B38*(1+INDEX($F$20:$F$32,MATCH(21,$E$20:$E$32,1)))/25,0)*25
A40: Year 22 | B40: =ROUND(B39*(1+INDEX($F$20:$F$32,MATCH(22,$E$20:$E$32,1)))/25,0)*25
A41: Year 23 | B41: =ROUND(B40*(1+INDEX($F$20:$F$32,MATCH(23,$E$20:$E$32,1)))/25,0)*25
A42: Year 24 | B42: =ROUND(B41*(1+INDEX($F$20:$F$32,MATCH(24,$E$20:$E$32,1)))/25,0)*25
A43: Year 25 | B43: =ROUND(B42*(1+INDEX($F$20:$F$32,MATCH(25,$E$20:$E$32,1)))/25,0)*25
A44: Year 26 | B44: =ROUND(B43*(1+INDEX($F$20:$F$32,MATCH(26,$E$20:$E$32,1)))/25,0)*25
A45: Year 27 | B45: =ROUND(B44*(1+INDEX($F$20:$F$32,MATCH(27,$E$20:$E$32,1)))/25,0)*25
A46: Year 28 | B46: =ROUND(B45*(1+INDEX($F$20:$F$32,MATCH(28,$E$20:$E$32,1)))/25,0)*25
A47: Year 29 | B47: =ROUND(B46*(1+INDEX($F$20:$F$32,MATCH(29,$E$20:$E$32,1)))/25,0)*25
A48: Year 30 | B48: =ROUND(B47*(1+INDEX($F$20:$F$32,MATCH(30,$E$20:$E$32,1)))/25,0)*25
A49: Year 31 | B49: =ROUND(B48*(1+INDEX($F$20:$F$32,MATCH(31,$E$20:$E$32,1)))/25,0)*25
A50: Year 32 | B50: =ROUND(B49*(1+INDEX($F$20:$F$32,MATCH(32,$E$20:$E$32,1)))/25,0)*25
A51: Year 33 | B51: =ROUND(B50*(1+INDEX($F$20:$F$32,MATCH(33,$E$20:$E$32,1)))/25,0)*25
A52: Year 34 | B52: =ROUND(B51*(1+INDEX($F$20:$F$32,MATCH(34,$E$20:$E$32,1)))/25,0)*25
A53: Year 35 | B53: =ROUND(B52*(1+INDEX($F$20:$F$32,MATCH(35,$E$20:$E$32,1)))/25,0)*25
A54: Year 36 | B54: =ROUND(B53*(1+INDEX($F$20:$F$32,MATCH(36,$E$20:$E$32,1)))/25,0)*25
A55: Year 37 | B55: =ROUND(B54*(1+INDEX($F$20:$F$32,MATCH(37,$E$20:$E$32,1)))/25,0)*25
A56: Year 38 | B56: =ROUND(B55*(1+INDEX($F$20:$F$32,MATCH(38,$E$20:$E$32,1)))/25,0)*25
A57: Year 39 | B57: =ROUND(B56*(1+INDEX($F$20:$F$32,MATCH(39,$E$20:$E$32,1)))/25,0)*25
A58: Year 40 | B58: =ROUND(B57*(1+INDEX($F$20:$F$32,MATCH(40,$E$20:$E$32,1)))/25,0)*25
A59: Yr 1 links to the Dashboard; every later year = prior year x (1 + its stage rate). Change the 13 yellow stage rates to reshape the whole ramp. Defaults honor the user's anchors: 35%/yr ages 26-28 (no kids), then tapering 15%->5%; crosses $5k/mo ~age 31, $7k ~34; cap ($40k, Dashboard) leaves the entire 50s uncapped and binds only ~age 62+.
A60: Implied contribution growth, monthly (yr1 → horizon) | B60: =(INDEX($B$19:$B$58,MIN(40,MAX(1,$B$9)))/Dashboard!$C$8)^(1/MAX(1,(MIN(40,$B$9)-1)*12))-1

Sheet Data
A1: Model Data — per-regime return statistics (matrix v9, monthly-only execution, Jan 2007–Sep 2026)
A2: Blue = editable assumption. Rotation sleeve only; options overlay excluded.
A4: Mean monthly return
B5: Growth | C5: Reflation | D5: Stagflation | E5: Deflation
A6: CONS | B6: 0.00729 | C6: 0.00828 | D6: 0.00398 | E6: 0.01164
A7: MOD | B7: 0.01371 | C7: 0.01118 | D7: 0.00648 | E7: 0.01795
A8: AGG | B8: 0.03308 | C8: 0.01427 | D8: 0.00804 | E8: 0.03473
A9: VAGG | B9: 0.04851 | C9: 0.01752 | D9: 0.00869 | E9: 0.04287
A11: Monthly standard deviation
B12: Growth | C12: Reflation | D12: Stagflation | E12: Deflation
A13: CONS | B13: 0.01753 | C13: 0.02252 | D13: 0.01519 | E13: 0.0323
A14: MOD | B14: 0.03052 | C14: 0.03221 | D14: 0.02411 | E14: 0.035
A15: AGG | B15: 0.09041 | C15: 0.04384 | D15: 0.03079 | E15: 0.07679
A16: VAGG | B16: 0.13714 | C16: 0.06011 | D16: 0.03353 | E16: 0.09958
A18: Regime structure & risk-free
B19: Growth | C19: Reflation | D19: Stagflation | E19: Deflation
A20: Share of months | B20: 0.321 | C20: 0.473 | D20: 0.08 | E20: 0.127
A21: Avg duration (months) | B21: 3.2 | C21: 5.3 | D21: 2.7 | E21: 2.3
A23: Risk-free rate (annual) | B23: 0.019

Sheet Methodology
A1: Methodology & Assumptions
A3: Glide path
A4: The Dashboard assigns a risk tier to each 5-year age block (age 25→65 = 8 decision points). The projection applies each block's tier return, switching automatically at block boundaries. Defaults de-risk with age: VAGG→AGG→MOD→CONS.
A6: Framework
A7: Four macro regimes (growth x inflation) classified monthly ex-ante (SPY & DBC vs 10-month SMAs, locked). Each tier = fixed allocation per regime (matrix v2). Per-tier expected returns blend per-regime statistics by the Settings regime mix, minus switch-cost drag.
A9: Contributions
A10: Year-by-year monthly schedule on Settings (defaults: $1,500/mo yr1 per user 2026 update; +20%/yr through yr5, +7%/yr after — anchored to user decade targets: >$5k/mo in 30s, >$7k in 40s, >$10k in 50s), capped on the Dashboard. Projection applies the exact schedule.
A12: Uncertainty
A13: Low/High paths and Statistics percentiles band the uncertainty of the AVERAGE growth rate (+/- s.e. = annual sd / sqrt(horizon years)). They are not drawdown bounds: backtested max drawdowns are CONS -13%, MOD -15%, AGG -37%, VAGG -51%, and a VAGG-heavy early glide will experience them.
A15: Return haircut
A16: Long-horizon compounding of raw backtest returns is not credible (edges decay; regimes shift; capacity and execution erode results). The Dashboard haircut (default 25%) scales all tier returns down before projecting. Set 0% to see raw-backtest numbers; treat those as an upper bound, not a plan.
A18: Evidence quality
... A28: Personal research tooling; not investment advice. Past and simulated performance do not guarantee future results.
