Workbook

Sheet Orders
A1: MONTHLY ORDER SHEET — QUADRANT ROTATION
A2: ="Ledger row: "&Data!$H$1&" · "&Data!$H$2&" · matrix "&Data!$H$3&" — regenerate monthly: python -m src.portfolio.orders_workbook"
A3: YELLOW cells are yours: pick the tier, enter total account value, list current holdings (example rows below show the format — overwrite the 0s). Everything else computes. Trade the SELL ALL rows first, then the book.
A5: Risk tier | C5: AGG | K5: tier idx | L5: =MATCH($C$5,{"CONS";"MOD";"AGG";"VAGG"},0)
A6: Total account value ($) | C6: 17500
A7: =settled cash + market value of current rotation positions
A10: Your current holdings | D10: This month's target book
A11: Ticker | B11: Value ($) | C11: Status | D11: Ticker | E11: Weight | F11: Target $ | G11: Held $ | H11: Action | I11: Trade $ (+buy / −sell)
A12: QQQ | B12: 0 | C12: =IF($A12="","",IF(COUNTIF($D$12:$D$19,$A12)>0,"in book","SELL ALL")) | D12: =IF(INDEX(Data!$A:$A,1+($L$5-1)*10+1)=0,"",INDEX(Data!$A:$A,1+($L$5-1)*10+1)) | E12: =IF($D12="","",INDEX(Data!$B:$B,1+($L$5-1)*10+1)) | F12: =IF($D12="","",ROUND(E12*$C$6,0)) | G12: =IF($D12="","",SUMIF($A$12:$A$21,$D12,$B$12:$B$21)) | H12: =IF($D12="","",IF(F12-G12>0,"BUY",IF((G12-F12)/$C$6>0.05,"SELL","HOLD"))) | I12: =IF($D12="","",IF(H12="BUY",F12-G12,IF(H12="SELL",-(G12-F12),0)))
A13: ERX | B13: 0 | C13: =IF($A13="","",IF(COUNTIF($D$12:$D$19,$A13)>0,"in book","SELL ALL")) | D13: =IF(INDEX(Data!$A:$A,2+($L$5-1)*10+1)=0,"",INDEX(Data!$A:$A,2+($L$5-1)*10+1)) | E13: =IF($D13="","",INDEX(Data!$B:$B,2+($L$5-1)*10+1)) | F13: =IF($D13="","",ROUND(E13*$C$6,0)) | G13: =IF($D13="","",SUMIF($A$12:$A$21,$D13,$B$12:$B$21)) | H13: =IF($D13="","",IF(F13-G13>0,"BUY",IF((G13-F13)/$C$6>0.05,"SELL","HOLD"))) | I13: =IF($D13="","",IF(H13="BUY",F13-G13,IF(H13="SELL",-(G13-F13),0)))
A14: GLD | B14: 0 | C14: =IF($A14="","",IF(COUNTIF($D$12:$D$19,$A14)>0,"in book","SELL ALL")) | D14: =IF(INDEX(Data!$A:$A,3+($L$5-1)*10+1)=0,"",INDEX(Data!$A:$A,3+($L$5-1)*10+1)) | E14: =IF($D14="","",INDEX(Data!$B:$B,3+($L$5-1)*10+1)) | F14: =IF($D14="","",ROUND(E14*$C$6,0)) | G14: =IF($D14="","",SUMIF($A$12:$A$21,$D14,$B$12:$B$21)) | H14: =IF($D14="","",IF(F14-G14>0,"BUY",IF((G14-F14)/$C$6>0.05,"SELL","HOLD"))) | I14: =IF($D14="","",IF(H14="BUY",F14-G14,IF(H14="SELL",-(G14-F14),0)))
A15: DBC | B15: 0 | C15: =IF($A15="","",IF(COUNTIF($D$12:$D$19,$A15)>0,"in book","SELL ALL")) | D15: =IF(INDEX(Data!$A:$A,4+($L$5-1)*10+1)=0,"",INDEX(Data!$A:$A,4+($L$5-1)*10+1)) | E15: =IF($D15="","",INDEX(Data!$B:$B,4+($L$5-1)*10+1)) | F15: =IF($D15="","",ROUND(E15*$C$6,0)) | G15: =IF($D15="","",SUMIF($A$12:$A$21,$D15,$B$12:$B$21)) | H15: =IF($D15="","",IF(F15-G15>0,"BUY",IF((G15-F15)/$C$6>0.05,"SELL","HOLD"))) | I15: =IF($D15="","",IF(H15="BUY",F15-G15,IF(H15="SELL",-(G15-F15),0)))
C16: =IF($A16="","",IF(COUNTIF($D$12:$D$19,$A16)>0,"in book","SELL ALL")) | D16: =IF(INDEX(Data!$A:$A,5+($L$5-1)*10+1)=0,"",INDEX(Data!$A:$A,5+($L$5-1)*10+1)) | E16: =IF($D16="","",INDEX(Data!$B:$B,5+($L$5-1)*10+1)) | F16: =IF($D16="","",ROUND(E16*$C$6,0)) | G16: =IF($D16="","",SUMIF($A$12:$A$21,$D16,$B$12:$B$21)) | H16: =IF($D16="","",IF(F16-G16>0,"BUY",IF((G16-F16)/$C$6>0.05,"SELL","HOLD"))) | I16: =IF($D16="","",IF(H16="BUY",F16-G16,IF(H16="SELL",-(G16-F16),0)))
C17: =IF($A17="","",IF(COUNTIF($D$12:$D$19,$A17)>0,"in book","SELL ALL")) | D17: =IF(INDEX(Data!$A:$A,6+($L$5-1)*10+1)=0,"",INDEX(Data!$A:$A,6+($L$5-1)*10+1)) | E17: =IF($D17="","",INDEX(Data!$B:$B,6+($L$5-1)*10+1)) | F17: =IF($D17="","",ROUND(E17*$C$6,0)) | G17: =IF($D17="","",SUMIF($A$12:$A$21,$D17,$B$12:$B$21)) | H17: =IF($D17="","",IF(F17-G17>0,"BUY",IF((G17-F17)/$C$6>0.05,"SELL","HOLD"))) | I17: =IF($D17="","",IF(H17="BUY",F17-G17,IF(H17="SELL",-(G17-F17),0)))
C18: =IF($A18="","",IF(COUNTIF($D$12:$D$19,$A18)>0,"in book","SELL ALL")) | D18: =IF(INDEX(Data!$A:$A,7+($L$5-1)*10+1)=0,"",INDEX(Data!$A:$A,7+($L$5-1)*10+1)) | E18: =IF($D18="","",INDEX(Data!$B:$B,7+($L$5-1)*10+1)) | F18: =IF($D18="","",ROUND(E18*$C$6,0)) | G18: =IF($D18="","",SUMIF($A$12:$A$21,$D18,$B$12:$B$21)) | H18: =IF($D18="","",IF(F18-G18>0,"BUY",IF((G18-F18)/$C$6>0.05,"SELL","HOLD"))) | I18: =IF($D18="","",IF(H18="BUY",F18-G18,IF(H18="SELL",-(G18-F18),0)))
C19: =IF($A19="","",IF(COUNTIF($D$12:$D$19,$A19)>0,"in book","SELL ALL")) | D19: =IF(INDEX(Data!$A:$A,8+($L$5-1)*10+1)=0,"",INDEX(Data!$A:$A,8+($L$5-1)*10+1)) | E19: =IF($D19="","",INDEX(Data!$B:$B,8+($L$5-1)*10+1)) | F19: =IF($D19="","",ROUND(E19*$C$6,0)) | G19: =IF($D19="","",SUMIF($A$12:$A$21,$D19,$B$12:$B$21)) | H19: =IF($D19="","",IF(F19-G19>0,"BUY",IF((G19-F19)/$C$6>0.05,"SELL","HOLD"))) | I19: =IF($D19="","",IF(H19="BUY",F19-G19,IF(H19="SELL",-(G19-F19),0)))
C20: =IF($A20="","",IF(COUNTIF($D$12:$D$19,$A20)>0,"in book","SELL ALL")) | D20: Totals | F20: =SUM(F12:F19) | I20: =SUM(I12:I19)
C21: =IF($A21="","",IF(COUNTIF($D$12:$D$19,$A21)>0,"in book","SELL ALL"))
A23: Off-book positions to SELL entirely (left table, SELL ALL rows) | C23: =SUMPRODUCT(($C$12:$C$21="SELL ALL")*$B$12:$B$21)
A24: Cash remainder after all trades | C24: =$C$6-SUM(F12:F19)
A26: Execution: sells first (SELL ALL rows, then book SELLs), then buys. Limit orders near the midpoint; IBKR order entry accepts these dollar amounts directly ('Amount in USD') with fractional shares on. Equity ETFs near the close; never miss a rotation waiting for the right hour (DEPLOYMENT.md).
A27: The 5pp drift band is built in: overweights inside the band read HOLD — do not sell them. HOLD/BUY logic matches src/portfolio/order_calc.py, which the automated executor also uses.

Sheet Data
A1: CONS | G1: Month | H1: 2026-10
A2: SPY | B2: 0.21 | G2: Quadrant | H2: REFLATION
A3: XLE | B3: 0.1593 | G3: Matrix | H3: v9 (restated from logged signals)
A4: GLD | B4: 0.1103
A5: DBC | B5: 0.2205
A6: SHY | B6: 0.3
A11: MOD
A12: SPY | B12: 0.3
A13: XLE | B13: 0.2275
A14: GLD | B14: 0.1575
A15: DBC | B15: 0.315
A21: AGG
A22: QQQ | B22: 0.3
A23: ERX | B23: 0.2275
A24: GLD | B24: 0.1575
A25: DBC | B25: 0.315
A31: VAGG
A32: TQQQ | B32: 0.3
A33: ERX | B33: 0.2275
A34: GLD | B34: 0.1575
A35: DBC | B35: 0.315

Sheet Weekly Watch
A1: WEEKLY REGIME WATCH — informational, trades nothing
A2: Distance of each price to its regime boundary (mean of the prior 9 completed monthly closes). Provisional = quadrant if the month ended that day. Only the monthly ledger row rotates money (TESTS.md entry 67).
A4: Date (UTC) | B4: SPY vs growth line | C4: DBC vs inflation line | D4: Provisional | E4: In force | F4: Divergence
A5: 2026-09-03 | B5: 0.071 | C5: 0.1549 | D5: REFLATION | E5: REFLATION | F5: no
A6: 2026-09-14 | B6: 0.0698 | C6: 0.1994 | D6: REFLATION | E6: REFLATION | F6: no
A7: 2026-09-21 | B7: 0.0688 | C7: 0.1911 | D7: REFLATION | E7: REFLATION | F7: no
A8: 2026-09-30 | B8: 0.0723 | C8: 0.1574 | D8: REFLATION | E8: REFLATION | F8: no
A9: 2026-10-01 | B9: 0.056 | C9: 0.124 | D9: REFLATION | E9: REFLATION | F9: no
A10: 2026-10-05 | B10: 0.0657 | C10: 0.1317 | D10: REFLATION | E10: REFLATION | F10: no
A11: 2026-10-12 | B11: 0.078 | C11: 0.1463 | D11: REFLATION | E11: REFLATION | F11: no
A12: 2026-10-19 | B12: 0.0568 | C12: 0.1734 | D12: REFLATION | E12: REFLATION | F12: no
A13: 2026-10-24 | B13: 0.0523 | C13: 0.1859 | D13: REFLATION | E13: REFLATION | F13: no
A16: Paper ledger mark-to-market (as of 2026-10-24)
A17: Tier | B17: Since | C17: Return | D17: Max drawdown | E17: Trading days
A18: CONS | B18: 2026-08-20 | C18: 0.017320795 | D18: -0.022049848 | E18: 45
A19: MOD | B19: 2026-08-20 | C19: 0.024783597 | D19: -0.030637268 | E19: 45
A20: AGG | B20: 2026-08-20 | C20: 0.04366982 | D20: -0.027044646 | E20: 45
A21: VAGG | B21: 2026-08-20 | C21: 0.0089017919 | D21: -0.055164674 | E21: 45
A22: SPY (bench) | B22: 2026-08-20 | C22: -0.0009741253 | D22: -0.024729352 | E22: 45
A23: Daily-rebalanced paper books from each ledger row's logged_at; SPY = buy-and-hold benchmark.
